{"v":"5.7.6","fr":60,"ip":0,"op":181,"w":500,"h":500,"nm":"1179-dragonfly-outline","ddd":0,"assets":[],"layers":[{"ddd":0,"ind":1,"ty":3,"nm":"02092020","sr":1,"ks":{"o":{"a":0,"k":0,"ix":11},"r":{"a":0,"k":0,"ix":10},"p":{"a":0,"k":[-105,15,0],"ix":2,"l":2},"a":{"a":0,"k":[60,60,0],"ix":1,"l":2},"s":{"a":0,"k":[100,100,100],"ix":6,"l":2}},"ao":0,"ef":[{"ty":5,"nm":"02092020002","np":3,"mn":"ADBE Checkbox Control","ix":1,"en":1,"ef":[{"ty":7,"nm":"Checkbox","mn":"ADBE Checkbox Control-0001","ix":1,"v":{"a":0,"k":1,"ix":1}}]}],"ip":0,"op":300,"st":0,"bm":0},{"ddd":0,"ind":3,"ty":3,"nm":"Color  & Stroke Change","sr":1,"ks":{"o":{"a":0,"k":0,"ix":11},"r":{"a":0,"k":0,"ix":10},"p":{"a":0,"k":[0,0],"ix":2,"l":2},"a":{"a":0,"k":[0,0,0],"ix":1,"l":2},"s":{"a":0,"k":[100,100,100],"ix":6,"l":2}},"ao":0,"ef":[{"ty":5,"nm":"Primary","np":3,"mn":"ADBE Color Control","ix":1,"en":1,"ef":[{"ty":2,"nm":"Color","mn":"ADBE Color Control-0001","ix":1,"v":{"a":0,"k":[0.070588238537,0.074509806931,0.192156866193,1],"ix":1}}]},{"ty":5,"nm":"Secondary","np":3,"mn":"ADBE Color Control","ix":2,"en":1,"ef":[{"ty":2,"nm":"Color","mn":"ADBE Color Control-0001","ix":1,"v":{"a":0,"k":[0.031372550875,0.658823549747,0.541176497936,1],"ix":1}}]},{"ty":5,"nm":"Stroke","np":3,"mn":"ADBE Slider Control","ix":3,"en":1,"ef":[{"ty":0,"nm":"Slider","mn":"ADBE Slider Control-0001","ix":1,"v":{"a":0,"k":70,"ix":1}}]},{"ty":5,"nm":"Axis","np":3,"mn":"ADBE Point Control","ix":4,"en":1,"ef":[{"ty":3,"nm":"Point","mn":"ADBE Point Control-0001","ix":1,"v":{"a":0,"k":[250,250],"ix":1}}]},{"ty":5,"nm":"Scale","np":3,"mn":"ADBE Slider Control","ix":5,"en":1,"ef":[{"ty":0,"nm":"Slider","mn":"ADBE Slider Control-0001","ix":1,"v":{"a":0,"k":100,"ix":1}}]}],"ip":0,"op":300,"st":0,"bm":0},{"ddd":0,"ind":4,"ty":3,"nm":"NULL","sr":1,"ks":{"o":{"a":0,"k":0,"ix":11},"r":{"a":0,"k":0,"ix":10},"p":{"a":0,"k":[250,250,0],"ix":2,"l":2,"x":"var $bm_rt;\n$bm_rt = thisComp.layer('Color  & Stroke Change').effect('Axis')('Point');"},"a":{"a":0,"k":[60,60,0],"ix":1,"l":2},"s":{"a":0,"k":[100,100,100],"ix":6,"l":2,"x":"var $bm_rt;\nvar temp;\ntemp = thisComp.layer('Color  & Stroke Change').effect('Scale')('Slider');\n$bm_rt = [\n    temp,\n    temp\n];"}},"ao":0,"ip":0,"op":300,"st":0,"bm":0},{"ddd":0,"ind":5,"ty":4,"nm":"Body","parent":4,"sr":1,"ks":{"o":{"a":0,"k":100,"ix":11},"r":{"a":0,"k":0,"ix":10},"p":{"a":1,"k":[{"i":{"x":0.667,"y":1},"o":{"x":0.333,"y":0},"t":0,"s":[59.813,57.063,0],"to":[0,0,0],"ti":[0,0,0]},{"i":{"x":0.667,"y":1},"o":{"x":0.333,"y":0},"t":61.207,"s":[59.813,97.063,0],"to":[0,0,0],"ti":[0,0,0]},{"i":{"x":0.667,"y":1},"o":{"x":0.333,"y":0},"t":120.375,"s":[59.813,27.063,0],"to":[0,0,0],"ti":[0,0,0]},{"t":180,"s":[59.813,57.063,0]}],"ix":2,"l":2},"a":{"a":0,"k":[249.814,247.212,0],"ix":1,"l":2},"s":{"a":0,"k":[100,100,100],"ix":6,"l":2}},"ao":0,"shapes":[{"ty":"gr","it":[{"ind":0,"ty":"sh","ix":1,"ks":{"a":0,"k":{"i":[[-5.171,0],[0,0],[-0.154,5.169],[0,0],[8.776,0],[0,0],[-0.261,-8.772],[0,0]],"o":[[0,0],[5.171,0],[0,0],[0.261,-8.772],[0,0],[-8.776,0],[0,0],[0.154,5.169]],"v":[[0,113.247],[0,113.247],[9.56,103.967],[15.555,-97.222],[0,-113.247],[0,-113.247],[-15.555,-97.222],[-9.56,103.967]],"c":true},"ix":2},"nm":"Path 1","mn":"ADBE Vector Shape - Group","hd":false},{"ty":"st","c":{"a":0,"k":[0.031372550875,0.639215707779,0.521568655968,1],"ix":3,"x":"var $bm_rt;\n$bm_rt = thisComp.layer('Color  & Stroke Change').effect('Secondary')('Color');"},"o":{"a":0,"k":100,"ix":4},"w":{"a":0,"k":12,"ix":5,"x":"var $bm_rt;\n$bm_rt = $bm_mul(17.2 \/ 100, thisComp.layer('Color  & Stroke Change').effect('Stroke')('Slider'));"},"lc":2,"lj":2,"bm":0,"nm":"Stroke 1","mn":"ADBE Vector Graphic - Stroke","hd":false},{"ty":"tr","p":{"a":0,"k":[250,269.844],"ix":2},"a":{"a":0,"k":[0,0],"ix":1},"s":{"a":0,"k":[100,100],"ix":3},"r":{"a":0,"k":0,"ix":6},"o":{"a":0,"k":100,"ix":7},"sk":{"a":0,"k":0,"ix":4},"sa":{"a":0,"k":0,"ix":5},"nm":"Transform"}],"nm":"Group 1","np":2,"cix":2,"bm":0,"ix":1,"mn":"ADBE Vector Group","hd":false},{"ty":"gr","it":[{"ind":0,"ty":"sh","ix":1,"ks":{"a":0,"k":{"i":[[0,0],[0,0],[0,7.28],[5.66,4.47],[0,0],[4.34,0],[6.51,-5.28],[0,-5.29],[-8.01,-1.8],[0,0]],"o":[[0,0],[8.01,-1.8],[0,-5.29],[0,0],[-6.69,-5.29],[-4.97,0],[-5.51,4.47],[0,7.28],[0,0],[0,0]],"v":[[13.755,18.61],[16.215,18.61],[29.515,5.75],[19.345,-9.56],[19.335,-9.56],[-0.005,-18.61],[-19.725,-9.57],[-29.515,5.75],[-16.215,18.61],[-13.755,18.61]],"c":false},"ix":2},"nm":"Path 1","mn":"ADBE Vector Shape - Group","hd":false},{"ty":"st","c":{"a":0,"k":[0.031372550875,0.639215707779,0.521568655968,1],"ix":3,"x":"var $bm_rt;\n$bm_rt = thisComp.layer('Color  & Stroke Change').effect('Secondary')('Color');"},"o":{"a":0,"k":100,"ix":4},"w":{"a":0,"k":12,"ix":5,"x":"var $bm_rt;\n$bm_rt = $bm_mul(17.2 \/ 100, thisComp.layer('Color  & Stroke Change').effect('Stroke')('Slider'));"},"lc":2,"lj":2,"bm":0,"nm":"Stroke 1","mn":"ADBE Vector Graphic - Stroke","hd":false},{"ty":"tr","p":{"a":0,"k":[250.001,146.254],"ix":2},"a":{"a":0,"k":[0,0],"ix":1},"s":{"a":0,"k":[100,100],"ix":3},"r":{"a":0,"k":0,"ix":6},"o":{"a":0,"k":100,"ix":7},"sk":{"a":0,"k":0,"ix":4},"sa":{"a":0,"k":0,"ix":5},"nm":"Transform"}],"nm":"Group 2","np":2,"cix":2,"bm":0,"ix":2,"mn":"ADBE Vector Group","hd":false},{"ty":"gr","it":[{"ty":"gr","it":[{"ind":0,"ty":"sh","ix":1,"ks":{"a":0,"k":{"i":[[0,0],[0,0],[0,0]],"o":[[0,0],[0,0],[0,0]],"v":[[10.418,12.182],[-7.044,3.366],[-10.418,-12.182]],"c":false},"ix":2},"nm":"Path 1","mn":"ADBE Vector Shape - Group","hd":false},{"ty":"st","c":{"a":0,"k":[0.031372550875,0.639215707779,0.521568655968,1],"ix":3,"x":"var $bm_rt;\n$bm_rt = thisComp.layer('Color  & Stroke Change').effect('Primary')('Color');"},"o":{"a":0,"k":100,"ix":4},"w":{"a":0,"k":12,"ix":5,"x":"var $bm_rt;\n$bm_rt = $bm_mul(17.2 \/ 100, thisComp.layer('Color  & Stroke Change').effect('Stroke')('Slider'));"},"lc":2,"lj":2,"bm":0,"nm":"Stroke 1","mn":"ADBE Vector Graphic - Stroke","hd":false},{"ty":"tr","p":{"a":0,"k":[218.87,123.515],"ix":2},"a":{"a":0,"k":[0,0],"ix":1},"s":{"a":0,"k":[100,100],"ix":3},"r":{"a":0,"k":0,"ix":6},"o":{"a":0,"k":100,"ix":7},"sk":{"a":0,"k":0,"ix":4},"sa":{"a":0,"k":0,"ix":5},"nm":"Transform"}],"nm":"Group 1","np":2,"cix":2,"bm":0,"ix":1,"mn":"ADBE Vector Group","hd":false},{"ty":"gr","it":[{"ind":0,"ty":"sh","ix":1,"ks":{"a":0,"k":{"i":[[0,0],[0,0],[0,0]],"o":[[0,0],[0,0],[0,0]],"v":[[-10.418,12.182],[7.044,3.366],[10.418,-12.182]],"c":false},"ix":2},"nm":"Path 1","mn":"ADBE Vector Shape - Group","hd":false},{"ty":"st","c":{"a":0,"k":[0.031372550875,0.639215707779,0.521568655968,1],"ix":3,"x":"var $bm_rt;\n$bm_rt = thisComp.layer('Color  & Stroke Change').effect('Primary')('Color');"},"o":{"a":0,"k":100,"ix":4},"w":{"a":0,"k":12,"ix":5,"x":"var $bm_rt;\n$bm_rt = $bm_mul(17.2 \/ 100, thisComp.layer('Color  & Stroke Change').effect('Stroke')('Slider'));"},"lc":2,"lj":2,"bm":0,"nm":"Stroke 1","mn":"ADBE Vector Graphic - Stroke","hd":false},{"ty":"tr","p":{"a":0,"k":[280.758,123.515],"ix":2},"a":{"a":0,"k":[0,0],"ix":1},"s":{"a":0,"k":[100,100],"ix":3},"r":{"a":0,"k":0,"ix":6},"o":{"a":0,"k":100,"ix":7},"sk":{"a":0,"k":0,"ix":4},"sa":{"a":0,"k":0,"ix":5},"nm":"Transform"}],"nm":"Group 2","np":2,"cix":2,"bm":0,"ix":2,"mn":"ADBE Vector Group","hd":false},{"ty":"tr","p":{"a":0,"k":[280.758,123.515],"ix":2},"a":{"a":0,"k":[280.758,123.515],"ix":1},"s":{"a":0,"k":[100,100],"ix":3},"r":{"a":0,"k":0,"ix":6},"o":{"a":0,"k":100,"ix":7},"sk":{"a":0,"k":0,"ix":4},"sa":{"a":0,"k":0,"ix":5},"nm":"Transform"}],"nm":"Group 3","np":2,"cix":2,"bm":0,"ix":3,"mn":"ADBE Vector Group","hd":false}],"ip":0,"op":844,"st":0,"bm":0},{"ddd":0,"ind":6,"ty":4,"nm":"outline 6","parent":5,"sr":1,"ks":{"o":{"a":0,"k":100,"ix":11},"r":{"a":0,"k":0,"ix":10},"p":{"a":0,"k":[337.167,235.559,0],"ix":2,"l":2},"a":{"a":0,"k":[0,0,0],"ix":1,"l":2},"s":{"a":0,"k":[-100,100,100],"ix":6,"l":2}},"ao":0,"shapes":[{"ty":"gr","it":[{"ind":0,"ty":"sh","ix":1,"ks":{"a":1,"k":[{"i":{"x":0.667,"y":1},"o":{"x":0.333,"y":0},"t":0,"s":[{"i":[[0,0],[41.104,-13.734],[3.18,0],[3.64,13.42],[-8.612,1.808],[0,0],[0,0],[0,0]],"o":[[0,0],[-3.076,1.028],[-13.14,0],[-2.05,-7.58],[53.734,-11.284],[0,0],[0,0],[0,0]],"v":[[72.519,-4.425],[-33.521,31.425],[-43.121,33.015],[-72.041,10.875],[-61.651,-6.025],[69.239,-33.015],[69.249,-33.015],[69.269,-33.015]],"c":false}]},{"i":{"x":0.833,"y":0.833},"o":{"x":0.333,"y":0},"t":4,"s":[{"i":[[0,0],[43.293,-1.964],[3.059,0.87],[-0.181,13.904],[-8.778,-0.617],[0,0],[0,0],[0,0]],"o":[[0,0],[-3.24,0.147],[-12.639,-3.595],[0.102,-7.852],[54.771,3.848],[0,0],[0,0],[0,0]],"v":[[72.519,-4.425],[-47.96,2.453],[-57.629,1.355],[-79.388,-27.852],[-64.771,-41.265],[69.239,-33.015],[69.249,-33.015],[69.269,-33.015]],"c":false}]},{"i":{"x":0.667,"y":1},"o":{"x":0.167,"y":0.167},"t":8,"s":[{"i":[[0,0],[42.477,-14.805],[3.169,0.263],[2.138,18.097],[-8.781,1.684],[0,0],[0,0],[0,0]],"o":[[0,0],[-3.179,1.108],[-13.095,-1.089],[-1.207,-10.221],[54.793,-10.51],[0,0],[0,0],[0,0]],"v":[[72.019,0.075],[-11.619,69.586],[-21.361,70.899],[-47.741,39.146],[-35.524,17.599],[68.739,-28.515],[68.749,-28.515],[68.769,-28.515]],"c":false}]},{"i":{"x":0.833,"y":0.833},"o":{"x":0.333,"y":0},"t":12,"s":[{"i":[[0,0],[28.478,-32.668],[2.742,-1.611],[9.931,9.733],[-6.508,5.922],[0,0],[0,0],[0,0]],"o":[[0,0],[-2.131,2.445],[-11.328,6.658],[-5.608,-5.496],[40.608,-36.955],[0,0],[0,0],[0,0]],"v":[[72.519,5.325],[0.826,63.342],[-6.645,69.577],[-42.796,65.143],[-42.401,45.309],[71.739,-25.015],[71.749,-25.015],[71.769,-25.015]],"c":false}]},{"i":{"x":0.667,"y":1},"o":{"x":0.167,"y":0.167},"t":16,"s":[{"i":[[0,0],[42.477,-14.805],[3.169,0.263],[2.138,18.097],[-8.781,1.684],[0,0],[0,0],[0,0]],"o":[[0,0],[-3.179,1.108],[-13.095,-1.089],[-1.207,-10.221],[54.793,-10.51],[0,0],[0,0],[0,0]],"v":[[72.519,-0.925],[-30.619,42.086],[-40.361,43.399],[-66.741,11.646],[-54.524,-9.901],[69.239,-29.515],[69.249,-29.515],[69.269,-29.515]],"c":false}]},{"i":{"x":0.833,"y":0.833},"o":{"x":0.333,"y":0},"t":20,"s":[{"i":[[0,0],[43.293,-1.964],[3.059,0.87],[-0.181,13.904],[-8.778,-0.617],[0,0],[0,0],[0,0]],"o":[[0,0],[-3.24,0.147],[-12.639,-3.595],[0.102,-7.852],[54.771,3.848],[0,0],[0,0],[0,0]],"v":[[72.519,-4.425],[-47.96,2.453],[-57.629,1.355],[-79.388,-27.852],[-64.771,-41.265],[69.239,-33.015],[69.249,-33.015],[69.269,-33.015]],"c":false}]},{"i":{"x":0.667,"y":1},"o":{"x":0.167,"y":0.167},"t":24,"s":[{"i":[[0,0],[42.477,-14.805],[3.169,0.263],[2.138,18.097],[-8.781,1.684],[0,0],[0,0],[0,0]],"o":[[0,0],[-3.179,1.108],[-13.095,-1.089],[-1.207,-10.221],[54.793,-10.51],[0,0],[0,0],[0,0]],"v":[[72.019,0.075],[-11.619,69.586],[-21.361,70.899],[-47.741,39.146],[-35.524,17.599],[68.739,-28.515],[68.749,-28.515],[68.769,-28.515]],"c":false}]},{"i":{"x":0.833,"y":0.833},"o":{"x":0.333,"y":0},"t":28,"s":[{"i":[[0,0],[28.478,-32.668],[2.742,-1.611],[9.931,9.733],[-6.508,5.922],[0,0],[0,0],[0,0]],"o":[[0,0],[-2.131,2.445],[-11.328,6.658],[-5.608,-5.496],[40.608,-36.955],[0,0],[0,0],[0,0]],"v":[[72.519,5.325],[0.826,63.342],[-6.645,69.577],[-42.796,65.143],[-42.401,45.309],[71.739,-25.015],[71.749,-25.015],[71.769,-25.015]],"c":false}]},{"i":{"x":0.667,"y":1},"o":{"x":0.167,"y":0.167},"t":32,"s":[{"i":[[0,0],[42.477,-14.805],[3.169,0.263],[2.138,18.097],[-8.781,1.684],[0,0],[0,0],[0,0]],"o":[[0,0],[-3.179,1.108],[-13.095,-1.089],[-1.207,-10.221],[54.793,-10.51],[0,0],[0,0],[0,0]],"v":[[72.519,-0.925],[-30.619,42.086],[-40.361,43.399],[-66.741,11.646],[-54.524,-9.901],[69.239,-29.515],[69.249,-29.515],[69.269,-29.515]],"c":false}]},{"i":{"x":0.833,"y":0.833},"o":{"x":0.333,"y":0},"t":36,"s":[{"i":[[0,0],[43.293,-1.964],[3.059,0.87],[-0.181,13.904],[-8.778,-0.617],[0,0],[0,0],[0,0]],"o":[[0,0],[-3.24,0.147],[-12.639,-3.595],[0.102,-7.852],[54.771,3.848],[0,0],[0,0],[0,0]],"v":[[72.519,-4.425],[-47.96,2.453],[-57.629,1.355],[-79.388,-27.852],[-64.771,-41.265],[69.239,-33.015],[69.249,-33.015],[69.269,-33.015]],"c":false}]},{"i":{"x":0.667,"y":1},"o":{"x":0.167,"y":0.167},"t":40,"s":[{"i":[[0,0],[42.477,-14.805],[3.169,0.263],[2.138,18.097],[-8.781,1.684],[0,0],[0,0],[0,0]],"o":[[0,0],[-3.179,1.108],[-13.095,-1.089],[-1.207,-10.221],[54.793,-10.51],[0,0],[0,0],[0,0]],"v":[[72.019,0.075],[-11.619,69.586],[-21.361,70.899],[-47.741,39.146],[-35.524,17.599],[68.739,-28.515],[68.749,-28.515],[68.769,-28.515]],"c":false}]},{"i":{"x":0.833,"y":0.833},"o":{"x":0.333,"y":0},"t":44,"s":[{"i":[[0,0],[28.478,-32.668],[2.742,-1.611],[9.931,9.733],[-6.508,5.922],[0,0],[0,0],[0,0]],"o":[[0,0],[-2.131,2.445],[-11.328,6.658],[-5.608,-5.496],[40.608,-36.955],[0,0],[0,0],[0,0]],"v":[[72.519,5.325],[0.826,63.342],[-6.645,69.577],[-42.796,65.143],[-42.401,45.309],[71.739,-25.015],[71.749,-25.015],[71.769,-25.015]],"c":false}]},{"i":{"x":0.667,"y":1},"o":{"x":0.167,"y":0.167},"t":48,"s":[{"i":[[0,0],[42.477,-14.805],[3.169,0.263],[2.138,18.097],[-8.781,1.684],[0,0],[0,0],[0,0]],"o":[[0,0],[-3.179,1.108],[-13.095,-1.089],[-1.207,-10.221],[54.793,-10.51],[0,0],[0,0],[0,0]],"v":[[72.519,-0.925],[-30.619,42.086],[-40.361,43.399],[-66.741,11.646],[-54.524,-9.901],[69.239,-29.515],[69.249,-29.515],[69.269,-29.515]],"c":false}]},{"i":{"x":0.833,"y":0.833},"o":{"x":0.333,"y":0},"t":52,"s":[{"i":[[0,0],[43.293,-1.964],[3.059,0.87],[-0.181,13.904],[-8.778,-0.617],[0,0],[0,0],[0,0]],"o":[[0,0],[-3.24,0.147],[-12.639,-3.595],[0.102,-7.852],[54.771,3.848],[0,0],[0,0],[0,0]],"v":[[72.519,-4.425],[-47.96,2.453],[-57.629,1.355],[-79.388,-27.852],[-64.771,-41.265],[69.239,-33.015],[69.249,-33.015],[69.269,-33.015]],"c":false}]},{"i":{"x":0.667,"y":1},"o":{"x":0.167,"y":0.167},"t":56,"s":[{"i":[[0,0],[42.477,-14.805],[3.169,0.263],[2.138,18.097],[-8.781,1.684],[0,0],[0,0],[0,0]],"o":[[0,0],[-3.179,1.108],[-13.095,-1.089],[-1.207,-10.221],[54.793,-10.51],[0,0],[0,0],[0,0]],"v":[[72.019,0.075],[-11.619,69.586],[-21.361,70.899],[-47.741,39.146],[-35.524,17.599],[68.739,-28.515],[68.749,-28.515],[68.769,-28.515]],"c":false}]},{"i":{"x":0.833,"y":0.833},"o":{"x":0.333,"y":0},"t":60,"s":[{"i":[[0,0],[28.478,-32.668],[2.742,-1.611],[9.931,9.733],[-6.508,5.922],[0,0],[0,0],[0,0]],"o":[[0,0],[-2.131,2.445],[-11.328,6.658],[-5.608,-5.496],[40.608,-36.955],[0,0],[0,0],[0,0]],"v":[[72.519,5.325],[0.826,63.342],[-6.645,69.577],[-42.796,65.143],[-42.401,45.309],[71.739,-25.015],[71.749,-25.015],[71.769,-25.015]],"c":false}]},{"i":{"x":0.667,"y":1},"o":{"x":0.167,"y":0.167},"t":64,"s":[{"i":[[0,0],[42.477,-14.805],[3.169,0.263],[2.138,18.097],[-8.781,1.684],[0,0],[0,0],[0,0]],"o":[[0,0],[-3.179,1.108],[-13.095,-1.089],[-1.207,-10.221],[54.793,-10.51],[0,0],[0,0],[0,0]],"v":[[72.519,-0.925],[-30.619,42.086],[-40.361,43.399],[-66.741,11.646],[-54.524,-9.901],[69.239,-29.515],[69.249,-29.515],[69.269,-29.515]],"c":false}]},{"i":{"x":0.833,"y":0.833},"o":{"x":0.333,"y":0},"t":68,"s":[{"i":[[0,0],[43.293,-1.964],[3.059,0.87],[-0.181,13.904],[-8.778,-0.617],[0,0],[0,0],[0,0]],"o":[[0,0],[-3.24,0.147],[-12.639,-3.595],[0.102,-7.852],[54.771,3.848],[0,0],[0,0],[0,0]],"v":[[72.519,-4.425],[-47.96,2.453],[-57.629,1.355],[-79.388,-27.852],[-64.771,-41.265],[69.239,-33.015],[69.249,-33.015],[69.269,-33.015]],"c":false}]},{"i":{"x":0.667,"y":1},"o":{"x":0.167,"y":0.167},"t":72,"s":[{"i":[[0,0],[42.477,-14.805],[3.169,0.263],[2.138,18.097],[-8.781,1.684],[0,0],[0,0],[0,0]],"o":[[0,0],[-3.179,1.108],[-13.095,-1.089],[-1.207,-10.221],[54.793,-10.51],[0,0],[0,0],[0,0]],"v":[[72.019,0.075],[-11.619,69.586],[-21.361,70.899],[-47.741,39.146],[-35.524,17.599],[68.739,-28.515],[68.749,-28.515],[68.769,-28.515]],"c":false}]},{"i":{"x":0.833,"y":0.833},"o":{"x":0.333,"y":0},"t":76,"s":[{"i":[[0,0],[28.478,-32.668],[2.742,-1.611],[9.931,9.733],[-6.508,5.922],[0,0],[0,0],[0,0]],"o":[[0,0],[-2.131,2.445],[-11.328,6.658],[-5.608,-5.496],[40.608,-36.955],[0,0],[0,0],[0,0]],"v":[[72.519,5.325],[0.826,63.342],[-6.645,69.577],[-42.796,65.143],[-42.401,45.309],[71.739,-25.015],[71.749,-25.015],[71.769,-25.015]],"c":false}]},{"i":{"x":0.667,"y":1},"o":{"x":0.167,"y":0.167},"t":80,"s":[{"i":[[0,0],[42.477,-14.805],[3.169,0.263],[2.138,18.097],[-8.781,1.684],[0,0],[0,0],[0,0]],"o":[[0,0],[-3.179,1.108],[-13.095,-1.089],[-1.207,-10.221],[54.793,-10.51],[0,0],[0,0],[0,0]],"v":[[72.519,-0.925],[-30.619,42.086],[-40.361,43.399],[-66.741,11.646],[-54.524,-9.901],[69.239,-29.515],[69.249,-29.515],[69.269,-29.515]],"c":false}]},{"i":{"x":0.833,"y":0.833},"o":{"x":0.333,"y":0},"t":84,"s":[{"i":[[0,0],[43.293,-1.964],[3.059,0.87],[-0.181,13.904],[-8.778,-0.617],[0,0],[0,0],[0,0]],"o":[[0,0],[-3.24,0.147],[-12.639,-3.595],[0.102,-7.852],[54.771,3.848],[0,0],[0,0],[0,0]],"v":[[72.519,-4.425],[-47.96,2.453],[-57.629,1.355],[-79.388,-27.852],[-64.771,-41.265],[69.239,-33.015],[69.249,-33.015],[69.269,-33.015]],"c":false}]},{"i":{"x":0.667,"y":1},"o":{"x":0.167,"y":0.167},"t":88,"s":[{"i":[[0,0],[42.477,-14.805],[3.169,0.263],[2.138,18.097],[-8.781,1.684],[0,0],[0,0],[0,0]],"o":[[0,0],[-3.179,1.108],[-13.095,-1.089],[-1.207,-10.221],[54.793,-10.51],[0,0],[0,0],[0,0]],"v":[[72.019,0.075],[-11.619,69.586],[-21.361,70.899],[-47.741,39.146],[-35.524,17.599],[68.739,-28.515],[68.749,-28.515],[68.769,-28.515]],"c":false}]},{"i":{"x":0.833,"y":0.833},"o":{"x":0.333,"y":0},"t":92,"s":[{"i":[[0,0],[28.478,-32.668],[2.742,-1.611],[9.931,9.733],[-6.508,5.922],[0,0],[0,0],[0,0]],"o":[[0,0],[-2.131,2.445],[-11.328,6.658],[-5.608,-5.496],[40.608,-36.955],[0,0],[0,0],[0,0]],"v":[[72.519,5.325],[0.826,63.342],[-6.645,69.577],[-42.796,65.143],[-42.401,45.309],[71.739,-25.015],[71.749,-25.015],[71.769,-25.015]],"c":false}]},{"i":{"x":0.667,"y":1},"o":{"x":0.167,"y":0.167},"t":96,"s":[{"i":[[0,0],[42.477,-14.805],[3.169,0.263],[2.138,18.097],[-8.781,1.684],[0,0],[0,0],[0,0]],"o":[[0,0],[-3.179,1.108],[-13.095,-1.089],[-1.207,-10.221],[54.793,-10.51],[0,0],[0,0],[0,0]],"v":[[72.519,-0.925],[-30.619,42.086],[-40.361,43.399],[-66.741,11.646],[-54.524,-9.901],[69.239,-29.515],[69.249,-29.515],[69.269,-29.515]],"c":false}]},{"i":{"x":0.833,"y":0.833},"o":{"x":0.333,"y":0},"t":100,"s":[{"i":[[0,0],[43.293,-1.964],[3.059,0.87],[-0.181,13.904],[-8.778,-0.617],[0,0],[0,0],[0,0]],"o":[[0,0],[-3.24,0.147],[-12.639,-3.595],[0.102,-7.852],[54.771,3.848],[0,0],[0,0],[0,0]],"v":[[72.519,-4.425],[-47.96,2.453],[-57.629,1.355],[-79.388,-27.852],[-64.771,-41.265],[69.239,-33.015],[69.249,-33.015],[69.269,-33.015]],"c":false}]},{"i":{"x":0.667,"y":1},"o":{"x":0.167,"y":0.167},"t":104,"s":[{"i":[[0,0],[42.477,-14.805],[3.169,0.263],[2.138,18.097],[-8.781,1.684],[0,0],[0,0],[0,0]],"o":[[0,0],[-3.179,1.108],[-13.095,-1.089],[-1.207,-10.221],[54.793,-10.51],[0,0],[0,0],[0,0]],"v":[[72.019,0.075],[-11.619,69.586],[-21.361,70.899],[-47.741,39.146],[-35.524,17.599],[68.739,-28.515],[68.749,-28.515],[68.769,-28.515]],"c":false}]},{"i":{"x":0.833,"y":0.833},"o":{"x":0.333,"y":0},"t":108,"s":[{"i":[[0,0],[28.478,-32.668],[2.742,-1.611],[9.931,9.733],[-6.508,5.922],[0,0],[0,0],[0,0]],"o":[[0,0],[-2.131,2.445],[-11.328,6.658],[-5.608,-5.496],[40.608,-36.955],[0,0],[0,0],[0,0]],"v":[[72.519,5.325],[0.826,63.342],[-6.645,69.577],[-42.796,65.143],[-42.401,45.309],[71.739,-25.015],[71.749,-25.015],[71.769,-25.015]],"c":false}]},{"i":{"x":0.667,"y":1},"o":{"x":0.167,"y":0.167},"t":112,"s":[{"i":[[0,0],[42.477,-14.805],[3.169,0.263],[2.138,18.097],[-8.781,1.684],[0,0],[0,0],[0,0]],"o":[[0,0],[-3.179,1.108],[-13.095,-1.089],[-1.207,-10.221],[54.793,-10.51],[0,0],[0,0],[0,0]],"v":[[72.519,-0.925],[-30.619,42.086],[-40.361,43.399],[-66.741,11.646],[-54.524,-9.901],[69.239,-29.515],[69.249,-29.515],[69.269,-29.515]],"c":false}]},{"i":{"x":0.833,"y":0.833},"o":{"x":0.333,"y":0},"t":116,"s":[{"i":[[0,0],[43.293,-1.964],[3.059,0.87],[-0.181,13.904],[-8.778,-0.617],[0,0],[0,0],[0,0]],"o":[[0,0],[-3.24,0.147],[-12.639,-3.595],[0.102,-7.852],[54.771,3.848],[0,0],[0,0],[0,0]],"v":[[72.519,-4.425],[-47.96,2.453],[-57.629,1.355],[-79.388,-27.852],[-64.771,-41.265],[69.239,-33.015],[69.249,-33.015],[69.269,-33.015]],"c":false}]},{"i":{"x":0.667,"y":1},"o":{"x":0.167,"y":0.167},"t":120,"s":[{"i":[[0,0],[42.477,-14.805],[3.169,0.263],[2.138,18.097],[-8.781,1.684],[0,0],[0,0],[0,0]],"o":[[0,0],[-3.179,1.108],[-13.095,-1.089],[-1.207,-10.221],[54.793,-10.51],[0,0],[0,0],[0,0]],"v":[[72.019,0.075],[-11.619,69.586],[-21.361,70.899],[-47.741,39.146],[-35.524,17.599],[68.739,-28.515],[68.749,-28.515],[68.769,-28.515]],"c":false}]},{"i":{"x":0.833,"y":0.833},"o":{"x":0.333,"y":0},"t":124,"s":[{"i":[[0,0],[28.478,-32.668],[2.742,-1.611],[9.931,9.733],[-6.508,5.922],[0,0],[0,0],[0,0]],"o":[[0,0],[-2.131,2.445],[-11.328,6.658],[-5.608,-5.496],[40.608,-36.955],[0,0],[0,0],[0,0]],"v":[[72.519,5.325],[0.826,63.342],[-6.645,69.577],[-42.796,65.143],[-42.401,45.309],[71.739,-25.015],[71.749,-25.015],[71.769,-25.015]],"c":false}]},{"i":{"x":0.667,"y":1},"o":{"x":0.167,"y":0.167},"t":128,"s":[{"i":[[0,0],[42.477,-14.805],[3.169,0.263],[2.138,18.097],[-8.781,1.684],[0,0],[0,0],[0,0]],"o":[[0,0],[-3.179,1.108],[-13.095,-1.089],[-1.207,-10.221],[54.793,-10.51],[0,0],[0,0],[0,0]],"v":[[72.519,-0.925],[-30.619,42.086],[-40.361,43.399],[-66.741,11.646],[-54.524,-9.901],[69.239,-29.515],[69.249,-29.515],[69.269,-29.515]],"c":false}]},{"i":{"x":0.833,"y":0.833},"o":{"x":0.333,"y":0},"t":132,"s":[{"i":[[0,0],[43.293,-1.964],[3.059,0.87],[-0.181,13.904],[-8.778,-0.617],[0,0],[0,0],[0,0]],"o":[[0,0],[-3.24,0.147],[-12.639,-3.595],[0.102,-7.852],[54.771,3.848],[0,0],[0,0],[0,0]],"v":[[72.519,-4.425],[-47.96,2.453],[-57.629,1.355],[-79.388,-27.852],[-64.771,-41.265],[69.239,-33.015],[69.249,-33.015],[69.269,-33.015]],"c":false}]},{"i":{"x":0.667,"y":1},"o":{"x":0.167,"y":0.167},"t":136,"s":[{"i":[[0,0],[42.477,-14.805],[3.169,0.263],[2.138,18.097],[-8.781,1.684],[0,0],[0,0],[0,0]],"o":[[0,0],[-3.179,1.108],[-13.095,-1.089],[-1.207,-10.221],[54.793,-10.51],[0,0],[0,0],[0,0]],"v":[[72.019,0.075],[-11.619,69.586],[-21.361,70.899],[-47.741,39.146],[-35.524,17.599],[68.739,-28.515],[68.749,-28.515],[68.769,-28.515]],"c":false}]},{"i":{"x":0.833,"y":0.833},"o":{"x":0.333,"y":0},"t":140,"s":[{"i":[[0,0],[28.478,-32.668],[2.742,-1.611],[9.931,9.733],[-6.508,5.922],[0,0],[0,0],[0,0]],"o":[[0,0],[-2.131,2.445],[-11.328,6.658],[-5.608,-5.496],[40.608,-36.955],[0,0],[0,0],[0,0]],"v":[[72.519,5.325],[0.826,63.342],[-6.645,69.577],[-42.796,65.143],[-42.401,45.309],[71.739,-25.015],[71.749,-25.015],[71.769,-25.015]],"c":false}]},{"i":{"x":0.667,"y":1},"o":{"x":0.167,"y":0.167},"t":144,"s":[{"i":[[0,0],[42.477,-14.805],[3.169,0.263],[2.138,18.097],[-8.781,1.684],[0,0],[0,0],[0,0]],"o":[[0,0],[-3.179,1.108],[-13.095,-1.089],[-1.207,-10.221],[54.793,-10.51],[0,0],[0,0],[0,0]],"v":[[72.519,-0.925],[-30.619,42.086],[-40.361,43.399],[-66.741,11.646],[-54.524,-9.901],[69.239,-29.515],[69.249,-29.515],[69.269,-29.515]],"c":false}]},{"i":{"x":0.833,"y":0.833},"o":{"x":0.333,"y":0},"t":148,"s":[{"i":[[0,0],[43.293,-1.964],[3.059,0.87],[-0.181,13.904],[-8.778,-0.617],[0,0],[0,0],[0,0]],"o":[[0,0],[-3.24,0.147],[-12.639,-3.595],[0.102,-7.852],[54.771,3.848],[0,0],[0,0],[0,0]],"v":[[72.519,-4.425],[-47.96,2.453],[-57.629,1.355],[-79.388,-27.852],[-64.771,-41.265],[69.239,-33.015],[69.249,-33.015],[69.269,-33.015]],"c":false}]},{"i":{"x":0.667,"y":1},"o":{"x":0.167,"y":0.167},"t":152,"s":[{"i":[[0,0],[42.477,-14.805],[3.169,0.263],[2.138,18.097],[-8.781,1.684],[0,0],[0,0],[0,0]],"o":[[0,0],[-3.179,1.108],[-13.095,-1.089],[-1.207,-10.221],[54.793,-10.51],[0,0],[0,0],[0,0]],"v":[[72.019,0.075],[-11.619,69.586],[-21.361,70.899],[-47.741,39.146],[-35.524,17.599],[68.739,-28.515],[68.749,-28.515],[68.769,-28.515]],"c":false}]},{"i":{"x":0.833,"y":0.833},"o":{"x":0.333,"y":0},"t":156,"s":[{"i":[[0,0],[28.478,-32.668],[2.742,-1.611],[9.931,9.733],[-6.508,5.922],[0,0],[0,0],[0,0]],"o":[[0,0],[-2.131,2.445],[-11.328,6.658],[-5.608,-5.496],[40.608,-36.955],[0,0],[0,0],[0,0]],"v":[[72.519,5.325],[0.826,63.342],[-6.645,69.577],[-42.796,65.143],[-42.401,45.309],[71.739,-25.015],[71.749,-25.015],[71.769,-25.015]],"c":false}]},{"i":{"x":0.667,"y":1},"o":{"x":0.167,"y":0.167},"t":160,"s":[{"i":[[0,0],[42.477,-14.805],[3.169,0.263],[2.138,18.097],[-8.781,1.684],[0,0],[0,0],[0,0]],"o":[[0,0],[-3.179,1.108],[-13.095,-1.089],[-1.207,-10.221],[54.793,-10.51],[0,0],[0,0],[0,0]],"v":[[72.519,-0.925],[-30.619,42.086],[-40.361,43.399],[-66.741,11.646],[-54.524,-9.901],[69.239,-29.515],[69.249,-29.515],[69.269,-29.515]],"c":false}]},{"i":{"x":0.11,"y":1},"o":{"x":0.333,"y":0},"t":164,"s":[{"i":[[0,0],[43.293,-1.964],[3.059,0.87],[-0.181,13.904],[-8.778,-0.617],[0,0],[0,0],[0,0]],"o":[[0,0],[-3.24,0.147],[-12.639,-3.595],[0.102,-7.852],[54.771,3.848],[0,0],[0,0],[0,0]],"v":[[72.519,-4.425],[-47.96,2.453],[-57.629,1.355],[-79.388,-27.852],[-64.771,-41.265],[69.239,-33.015],[69.249,-33.015],[69.269,-33.015]],"c":false}]},{"t":180,"s":[{"i":[[0,0],[41.104,-13.734],[3.18,0],[3.64,13.42],[-8.612,1.808],[0,0],[0,0],[0,0]],"o":[[0,0],[-3.076,1.028],[-13.14,0],[-2.05,-7.58],[53.734,-11.284],[0,0],[0,0],[0,0]],"v":[[72.519,-4.425],[-33.521,31.425],[-43.121,33.015],[-72.041,10.875],[-61.651,-6.025],[69.239,-33.015],[69.249,-33.015],[69.269,-33.015]],"c":false}]}],"ix":2},"nm":"Path 1","mn":"ADBE Vector Shape - Group","hd":false},{"ty":"tm","s":{"a":0,"k":0,"ix":1},"e":{"a":1,"k":[{"i":{"x":[0.833],"y":[0.833]},"o":{"x":[0.167],"y":[0.167]},"t":0,"s":[100]},{"i":{"x":[0.833],"y":[0.833]},"o":{"x":[0.167],"y":[0.167]},"t":2,"s":[100]},{"i":{"x":[0.833],"y":[0.833]},"o":{"x":[0.167],"y":[0.167]},"t":3,"s":[59]},{"i":{"x":[0.833],"y":[0.833]},"o":{"x":[0.167],"y":[0.167]},"t":4,"s":[53]},{"i":{"x":[0.833],"y":[0.833]},"o":{"x":[0.167],"y":[0.167]},"t":5,"s":[49]},{"i":{"x":[0.833],"y":[0.833]},"o":{"x":[0.167],"y":[0.167]},"t":6,"s":[51.5]},{"i":{"x":[0.833],"y":[0.833]},"o":{"x":[0.167],"y":[0.167]},"t":8,"s":[56]},{"i":{"x":[0.833],"y":[0.833]},"o":{"x":[0.167],"y":[0.167]},"t":10,"s":[59]},{"i":{"x":[0.833],"y":[0.833]},"o":{"x":[0.167],"y":[0.167]},"t":11,"s":[54]},{"i":{"x":[0.833],"y":[0.833]},"o":{"x":[0.167],"y":[0.167]},"t":12,"s":[56]},{"i":{"x":[0.833],"y":[0.833]},"o":{"x":[0.167],"y":[0.167]},"t":13,"s":[57.5]},{"i":{"x":[0.833],"y":[0.833]},"o":{"x":[0.167],"y":[0.167]},"t":14,"s":[57]},{"i":{"x":[0.833],"y":[0.833]},"o":{"x":[0.167],"y":[0.167]},"t":15,"s":[100]},{"i":{"x":[0.833],"y":[0.833]},"o":{"x":[0.167],"y":[0.167]},"t":16,"s":[100]},{"i":{"x":[0.833],"y":[0.833]},"o":{"x":[0.167],"y":[0.167]},"t":18,"s":[100]},{"i":{"x":[0.833],"y":[0.833]},"o":{"x":[0.167],"y":[0.167]},"t":19,"s":[59]},{"i":{"x":[0.833],"y":[0.833]},"o":{"x":[0.167],"y":[0.167]},"t":20,"s":[53]},{"i":{"x":[0.833],"y":[0.833]},"o":{"x":[0.167],"y":[0.167]},"t":21,"s":[49]},{"i":{"x":[0.833],"y":[0.833]},"o":{"x":[0.167],"y":[0.167]},"t":22,"s":[51.5]},{"i":{"x":[0.833],"y":[0.833]},"o":{"x":[0.167],"y":[0.167]},"t":24,"s":[56]},{"i":{"x":[0.833],"y":[0.833]},"o":{"x":[0.167],"y":[0.167]},"t":26,"s":[59]},{"i":{"x":[0.833],"y":[0.833]},"o":{"x":[0.167],"y":[0.167]},"t":27,"s":[54]},{"i":{"x":[0.833],"y":[0.833]},"o":{"x":[0.167],"y":[0.167]},"t":28,"s":[56]},{"i":{"x":[0.833],"y":[0.833]},"o":{"x":[0.167],"y":[0.167]},"t":29,"s":[57.5]},{"i":{"x":[0.833],"y":[0.833]},"o":{"x":[0.167],"y":[0.167]},"t":30,"s":[57]},{"i":{"x":[0.833],"y":[0.833]},"o":{"x":[0.167],"y":[0.167]},"t":31,"s":[100]},{"i":{"x":[0.833],"y":[0.833]},"o":{"x":[0.167],"y":[0.167]},"t":32,"s":[100]},{"i":{"x":[0.833],"y":[0.833]},"o":{"x":[0.167],"y":[0.167]},"t":34,"s":[100]},{"i":{"x":[0.833],"y":[0.833]},"o":{"x":[0.167],"y":[0.167]},"t":35,"s":[59]},{"i":{"x":[0.833],"y":[0.833]},"o":{"x":[0.167],"y":[0.167]},"t":36,"s":[53]},{"i":{"x":[0.833],"y":[0.833]},"o":{"x":[0.167],"y":[0.167]},"t":37,"s":[49]},{"i":{"x":[0.833],"y":[0.833]},"o":{"x":[0.167],"y":[0.167]},"t":38,"s":[51.5]},{"i":{"x":[0.833],"y":[0.833]},"o":{"x":[0.167],"y":[0.167]},"t":40,"s":[56]},{"i":{"x":[0.833],"y":[0.833]},"o":{"x":[0.167],"y":[0.167]},"t":42,"s":[59]},{"i":{"x":[0.833],"y":[0.833]},"o":{"x":[0.167],"y":[0.167]},"t":43,"s":[54]},{"i":{"x":[0.833],"y":[0.833]},"o":{"x":[0.167],"y":[0.167]},"t":44,"s":[56]},{"i":{"x":[0.833],"y":[0.833]},"o":{"x":[0.167],"y":[0.167]},"t":45,"s":[57.5]},{"i":{"x":[0.833],"y":[0.833]},"o":{"x":[0.167],"y":[0.167]},"t":46,"s":[57]},{"i":{"x":[0.833],"y":[0.833]},"o":{"x":[0.167],"y":[0.167]},"t":47,"s":[100]},{"i":{"x":[0.833],"y":[0.833]},"o":{"x":[0.167],"y":[0.167]},"t":48,"s":[100]},{"i":{"x":[0.833],"y":[0.833]},"o":{"x":[0.167],"y":[0.167]},"t":50,"s":[100]},{"i":{"x":[0.833],"y":[0.833]},"o":{"x":[0.167],"y":[0.167]},"t":51,"s":[59]},{"i":{"x":[0.833],"y":[0.833]},"o":{"x":[0.167],"y":[0.167]},"t":52,"s":[53]},{"i":{"x":[0.833],"y":[0.833]},"o":{"x":[0.167],"y":[0.167]},"t":53,"s":[49]},{"i":{"x":[0.833],"y":[0.833]},"o":{"x":[0.167],"y":[0.167]},"t":54,"s":[51.5]},{"i":{"x":[0.833],"y":[0.833]},"o":{"x":[0.167],"y":[0.167]},"t":56,"s":[56]},{"i":{"x":[0.833],"y":[0.833]},"o":{"x":[0.167],"y":[0.167]},"t":58,"s":[59]},{"i":{"x":[0.833],"y":[0.833]},"o":{"x":[0.167],"y":[0.167]},"t":59,"s":[54]},{"i":{"x":[0.833],"y":[0.833]},"o":{"x":[0.167],"y":[0.167]},"t":60,"s":[56]},{"i":{"x":[0.833],"y":[0.833]},"o":{"x":[0.167],"y":[0.167]},"t":61,"s":[57.5]},{"i":{"x":[0.833],"y":[0.833]},"o":{"x":[0.167],"y":[0.167]},"t":62,"s":[57]},{"i":{"x":[0.833],"y":[0.833]},"o":{"x":[0.167],"y":[0.167]},"t":63,"s":[100]},{"i":{"x":[0.833],"y":[0.833]},"o":{"x":[0.167],"y":[0.167]},"t":64,"s":[100]},{"i":{"x":[0.833],"y":[0.833]},"o":{"x":[0.167],"y":[0.167]},"t":66,"s":[100]},{"i":{"x":[0.833],"y":[0.833]},"o":{"x":[0.167],"y":[0.167]},"t":67,"s":[59]},{"i":{"x":[0.833],"y":[0.833]},"o":{"x":[0.167],"y":[0.167]},"t":68,"s":[53]},{"i":{"x":[0.833],"y":[0.833]},"o":{"x":[0.167],"y":[0.167]},"t":69,"s":[49]},{"i":{"x":[0.833],"y":[0.833]},"o":{"x":[0.167],"y":[0.167]},"t":70,"s":[51.5]},{"i":{"x":[0.833],"y":[0.833]},"o":{"x":[0.167],"y":[0.167]},"t":72,"s":[56]},{"i":{"x":[0.833],"y":[0.833]},"o":{"x":[0.167],"y":[0.167]},"t":74,"s":[59]},{"i":{"x":[0.833],"y":[0.833]},"o":{"x":[0.167],"y":[0.167]},"t":75,"s":[54]},{"i":{"x":[0.833],"y":[0.833]},"o":{"x":[0.167],"y":[0.167]},"t":76,"s":[56]},{"i":{"x":[0.833],"y":[0.833]},"o":{"x":[0.167],"y":[0.167]},"t":77,"s":[57.5]},{"i":{"x":[0.833],"y":[0.833]},"o":{"x":[0.167],"y":[0.167]},"t":78,"s":[57]},{"i":{"x":[0.833],"y":[0.833]},"o":{"x":[0.167],"y":[0.167]},"t":79,"s":[100]},{"i":{"x":[0.833],"y":[0.833]},"o":{"x":[0.167],"y":[0.167]},"t":80,"s":[100]},{"i":{"x":[0.833],"y":[0.833]},"o":{"x":[0.167],"y":[0.167]},"t":82,"s":[100]},{"i":{"x":[0.833],"y":[0.833]},"o":{"x":[0.167],"y":[0.167]},"t":83,"s":[59]},{"i":{"x":[0.833],"y":[0.833]},"o":{"x":[0.167],"y":[0.167]},"t":84,"s":[53]},{"i":{"x":[0.833],"y":[0.833]},"o":{"x":[0.167],"y":[0.167]},"t":85,"s":[49]},{"i":{"x":[0.833],"y":[0.833]},"o":{"x":[0.167],"y":[0.167]},"t":86,"s":[51.5]},{"i":{"x":[0.833],"y":[0.833]},"o":{"x":[0.167],"y":[0.167]},"t":88,"s":[56]},{"i":{"x":[0.833],"y":[0.833]},"o":{"x":[0.167],"y":[0.167]},"t":90,"s":[59]},{"i":{"x":[0.833],"y":[0.833]},"o":{"x":[0.167],"y":[0.167]},"t":91,"s":[54]},{"i":{"x":[0.833],"y":[0.833]},"o":{"x":[0.167],"y":[0.167]},"t":92,"s":[56]},{"i":{"x":[0.833],"y":[0.833]},"o":{"x":[0.167],"y":[0.167]},"t":93,"s":[57.5]},{"i":{"x":[0.833],"y":[0.833]},"o":{"x":[0.167],"y":[0.167]},"t":94,"s":[57]},{"i":{"x":[0.833],"y":[0.833]},"o":{"x":[0.167],"y":[0.167]},"t":95,"s":[100]},{"i":{"x":[0.833],"y":[0.833]},"o":{"x":[0.167],"y":[0.167]},"t":96,"s":[100]},{"i":{"x":[0.833],"y":[0.833]},"o":{"x":[0.167],"y":[0.167]},"t":98,"s":[100]},{"i":{"x":[0.833],"y":[0.833]},"o":{"x":[0.167],"y":[0.167]},"t":99,"s":[59]},{"i":{"x":[0.833],"y":[0.833]},"o":{"x":[0.167],"y":[0.167]},"t":100,"s":[53]},{"i":{"x":[0.833],"y":[0.833]},"o":{"x":[0.167],"y":[0.167]},"t":101,"s":[49]},{"i":{"x":[0.833],"y":[0.833]},"o":{"x":[0.167],"y":[0.167]},"t":102,"s":[51.5]},{"i":{"x":[0.833],"y":[0.833]},"o":{"x":[0.167],"y":[0.167]},"t":104,"s":[56]},{"i":{"x":[0.833],"y":[0.833]},"o":{"x":[0.167],"y":[0.167]},"t":106,"s":[59]},{"i":{"x":[0.833],"y":[0.833]},"o":{"x":[0.167],"y":[0.167]},"t":107,"s":[54]},{"i":{"x":[0.833],"y":[0.833]},"o":{"x":[0.167],"y":[0.167]},"t":108,"s":[56]},{"i":{"x":[0.833],"y":[0.833]},"o":{"x":[0.167],"y":[0.167]},"t":109,"s":[57.5]},{"i":{"x":[0.833],"y":[0.833]},"o":{"x":[0.167],"y":[0.167]},"t":110,"s":[57]},{"i":{"x":[0.833],"y":[0.833]},"o":{"x":[0.167],"y":[0.167]},"t":111,"s":[100]},{"i":{"x":[0.833],"y":[0.833]},"o":{"x":[0.167],"y":[0.167]},"t":112,"s":[100]},{"i":{"x":[0.833],"y":[0.833]},"o":{"x":[0.167],"y":[0.167]},"t":114,"s":[100]},{"i":{"x":[0.833],"y":[0.833]},"o":{"x":[0.167],"y":[0.167]},"t":115,"s":[59]},{"i":{"x":[0.833],"y":[0.833]},"o":{"x":[0.167],"y":[0.167]},"t":116,"s":[53]},{"i":{"x":[0.833],"y":[0.833]},"o":{"x":[0.167],"y":[0.167]},"t":117,"s":[49]},{"i":{"x":[0.833],"y":[0.833]},"o":{"x":[0.167],"y":[0.167]},"t":118,"s":[51.5]},{"i":{"x":[0.833],"y":[0.833]},"o":{"x":[0.167],"y":[0.167]},"t":120,"s":[56]},{"i":{"x":[0.833],"y":[0.833]},"o":{"x":[0.167],"y":[0.167]},"t":122,"s":[59]},{"i":{"x":[0.833],"y":[0.833]},"o":{"x":[0.167],"y":[0.167]},"t":123,"s":[54]},{"i":{"x":[0.833],"y":[0.833]},"o":{"x":[0.167],"y":[0.167]},"t":124,"s":[56]},{"i":{"x":[0.833],"y":[0.833]},"o":{"x":[0.167],"y":[0.167]},"t":125,"s":[57.5]},{"i":{"x":[0.833],"y":[0.833]},"o":{"x":[0.167],"y":[0.167]},"t":126,"s":[57]},{"i":{"x":[0.833],"y":[0.833]},"o":{"x":[0.167],"y":[0.167]},"t":127,"s":[100]},{"i":{"x":[0.833],"y":[0.833]},"o":{"x":[0.167],"y":[0.167]},"t":128,"s":[100]},{"i":{"x":[0.833],"y":[0.833]},"o":{"x":[0.167],"y":[0.167]},"t":130,"s":[100]},{"i":{"x":[0.833],"y":[0.833]},"o":{"x":[0.167],"y":[0.167]},"t":131,"s":[59]},{"i":{"x":[0.833],"y":[0.833]},"o":{"x":[0.167],"y":[0.167]},"t":132,"s":[53]},{"i":{"x":[0.833],"y":[0.833]},"o":{"x":[0.167],"y":[0.167]},"t":133,"s":[49]},{"i":{"x":[0.833],"y":[0.833]},"o":{"x":[0.167],"y":[0.167]},"t":134,"s":[51.5]},{"i":{"x":[0.833],"y":[0.833]},"o":{"x":[0.167],"y":[0.167]},"t":136,"s":[56]},{"i":{"x":[0.833],"y":[0.833]},"o":{"x":[0.167],"y":[0.167]},"t":138,"s":[59]},{"i":{"x":[0.833],"y":[0.833]},"o":{"x":[0.167],"y":[0.167]},"t":139,"s":[54]},{"i":{"x":[0.833],"y":[0.833]},"o":{"x":[0.167],"y":[0.167]},"t":140,"s":[56]},{"i":{"x":[0.833],"y":[0.833]},"o":{"x":[0.167],"y":[0.167]},"t":141,"s":[57.5]},{"i":{"x":[0.833],"y":[0.833]},"o":{"x":[0.167],"y":[0.167]},"t":142,"s":[57]},{"i":{"x":[0.833],"y":[0.833]},"o":{"x":[0.167],"y":[0.167]},"t":143,"s":[100]},{"i":{"x":[0.833],"y":[0.833]},"o":{"x":[0.167],"y":[0.167]},"t":144,"s":[100]},{"i":{"x":[0.833],"y":[0.833]},"o":{"x":[0.167],"y":[0.167]},"t":146,"s":[100]},{"i":{"x":[0.833],"y":[0.833]},"o":{"x":[0.167],"y":[0.167]},"t":147,"s":[59]},{"i":{"x":[0.833],"y":[0.833]},"o":{"x":[0.167],"y":[0.167]},"t":148,"s":[53]},{"i":{"x":[0.833],"y":[0.833]},"o":{"x":[0.167],"y":[0.167]},"t":149,"s":[49]},{"i":{"x":[0.833],"y":[0.833]},"o":{"x":[0.167],"y":[0.167]},"t":150,"s":[51.5]},{"i":{"x":[0.833],"y":[0.833]},"o":{"x":[0.167],"y":[0.167]},"t":152,"s":[56]},{"i":{"x":[0.833],"y":[0.833]},"o":{"x":[0.167],"y":[0.167]},"t":154,"s":[59]},{"i":{"x":[0.833],"y":[0.833]},"o":{"x":[0.167],"y":[0.167]},"t":155,"s":[54]},{"i":{"x":[0.833],"y":[0.833]},"o":{"x":[0.167],"y":[0.167]},"t":156,"s":[56]},{"i":{"x":[0.833],"y":[0.833]},"o":{"x":[0.167],"y":[0.167]},"t":157,"s":[57.5]},{"i":{"x":[0.833],"y":[0.833]},"o":{"x":[0.167],"y":[0.167]},"t":158,"s":[57]},{"i":{"x":[0.833],"y":[0.833]},"o":{"x":[0.167],"y":[0.167]},"t":159,"s":[100]},{"i":{"x":[0.833],"y":[0.833]},"o":{"x":[0.167],"y":[0.167]},"t":160,"s":[100]},{"i":{"x":[0.833],"y":[0.833]},"o":{"x":[0.167],"y":[0.167]},"t":162,"s":[100]},{"i":{"x":[0.833],"y":[0.833]},"o":{"x":[0.167],"y":[0.167]},"t":163,"s":[59]},{"i":{"x":[0.11],"y":[1]},"o":{"x":[0.167],"y":[0.167]},"t":164,"s":[60]},{"t":165,"s":[100]}],"ix":2},"o":{"a":0,"k":0,"ix":3},"m":1,"ix":2,"nm":"Trim Paths 1","mn":"ADBE Vector Filter - Trim","hd":false},{"ty":"st","c":{"a":0,"k":[0.031372550875,0.639215707779,0.521568655968,1],"ix":3,"x":"var $bm_rt;\n$bm_rt = thisComp.layer('Color  & Stroke Change').effect('Primary')('Color');"},"o":{"a":0,"k":100,"ix":4},"w":{"a":0,"k":12,"ix":5,"x":"var $bm_rt;\n$bm_rt = $bm_mul(17.2 \/ 100, thisComp.layer('Color  & Stroke Change').effect('Stroke')('Slider'));"},"lc":2,"lj":2,"bm":0,"nm":"Stroke 1","mn":"ADBE Vector Graphic - Stroke","hd":false},{"ty":"tr","p":{"a":0,"k":[0,0],"ix":2},"a":{"a":0,"k":[0,0],"ix":1},"s":{"a":0,"k":[100,100],"ix":3},"r":{"a":0,"k":0,"ix":6},"o":{"a":0,"k":100,"ix":7},"sk":{"a":0,"k":0,"ix":4},"sa":{"a":0,"k":0,"ix":5},"nm":"Transform"}],"nm":"Group 1","np":3,"cix":2,"bm":0,"ix":1,"mn":"ADBE Vector Group","hd":false}],"ip":0,"op":844,"st":0,"bm":0},{"ddd":0,"ind":7,"ty":4,"nm":"outline 5","parent":5,"sr":1,"ks":{"o":{"a":0,"k":100,"ix":11},"r":{"a":0,"k":0,"ix":10},"p":{"a":0,"k":[343.356,188.286,0],"ix":2,"l":2},"a":{"a":0,"k":[0,0,0],"ix":1,"l":2},"s":{"a":0,"k":[-100,100,100],"ix":6,"l":2}},"ao":0,"shapes":[{"ty":"gr","it":[{"ind":0,"ty":"sh","ix":1,"ks":{"a":1,"k":[{"i":{"x":0.667,"y":1},"o":{"x":0.333,"y":0},"t":0,"s":[{"i":[[0,0],[51.664,2.986],[0,-7.86],[-16.383,0.937],[0,0]],"o":[[0,0],[-9.583,-0.554],[0,16.64],[71.434,-4.084],[0,0]],"v":[[77.17,-13.132],[-63.52,-21.772],[-77.98,-8.172],[-48.04,21.798],[77.98,14.108]],"c":false}]},{"i":{"x":0.833,"y":0.833},"o":{"x":0.333,"y":0},"t":2,"s":[{"i":[[0,0],[50.593,10.883],[1.207,-7.767],[-16.333,-1.59],[0,0]],"o":[[0,0],[-9.385,-2.019],[-2.555,16.443],[71.214,6.933],[0,0]],"v":[[77.17,-13.132],[-59.216,-39.574],[-75.593,-28.355],[-50.61,5.856],[77.98,14.108]],"c":false}]},{"i":{"x":0.667,"y":1},"o":{"x":0.167,"y":0.167},"t":5,"s":[{"i":[[0,0],[49.301,15.906],[2.364,-9.715],[-16.2,-2.716],[0,0]],"o":[[0,0],[-9.145,-2.95],[-5.004,20.567],[70.637,11.842],[0,0]],"v":[[77.17,-13.132],[-56.133,-10.273],[-74.274,3.117],[-54.196,47.238],[77.98,14.108]],"c":false}]},{"i":{"x":0.833,"y":0.833},"o":{"x":0.333,"y":0},"t":10,"s":[{"i":[[0,0],[35.382,-37.766],[-6.036,-5.034],[-9.773,13.182],[0,0]],"o":[[0,0],[-6.563,7.005],[12.78,10.657],[42.614,-57.477],[0,0]],"v":[[77.17,-13.132],[-31.872,83.202],[-30.689,103.017],[11.504,99.218],[77.73,25.358]],"c":false}]},{"i":{"x":0.667,"y":1},"o":{"x":0.167,"y":0.167},"t":14,"s":[{"i":[[0,0],[58.934,-25.51],[-5.619,-10.781],[-17.342,10.673],[0,0]],"o":[[0,0],[-10.932,4.732],[11.897,22.824],[75.614,-46.536],[0,0]],"v":[[77.17,-13.132],[-70.555,17.203],[-76.729,44.143],[-22.387,68.094],[77.98,14.108]],"c":false}]},{"i":{"x":0.833,"y":0.833},"o":{"x":0.333,"y":0},"t":18,"s":[{"i":[[0,0],[50.593,10.883],[1.207,-7.767],[-16.333,-1.59],[0,0]],"o":[[0,0],[-9.385,-2.019],[-2.555,16.443],[71.214,6.933],[0,0]],"v":[[77.17,-13.132],[-59.216,-39.574],[-75.593,-28.355],[-50.61,5.856],[77.98,14.108]],"c":false}]},{"i":{"x":0.667,"y":1},"o":{"x":0.167,"y":0.167},"t":21,"s":[{"i":[[0,0],[49.301,15.906],[2.364,-9.715],[-16.2,-2.716],[0,0]],"o":[[0,0],[-9.145,-2.95],[-5.004,20.567],[70.637,11.842],[0,0]],"v":[[77.17,-13.132],[-56.133,-10.273],[-74.274,3.117],[-54.196,47.238],[77.98,14.108]],"c":false}]},{"i":{"x":0.833,"y":0.833},"o":{"x":0.333,"y":0},"t":26,"s":[{"i":[[0,0],[35.382,-37.766],[-6.036,-5.034],[-9.773,13.182],[0,0]],"o":[[0,0],[-6.563,7.005],[12.78,10.657],[42.614,-57.477],[0,0]],"v":[[77.17,-13.132],[-31.872,83.202],[-30.689,103.017],[11.504,99.218],[77.73,25.358]],"c":false}]},{"i":{"x":0.667,"y":1},"o":{"x":0.167,"y":0.167},"t":30,"s":[{"i":[[0,0],[58.934,-25.51],[-5.619,-10.781],[-17.342,10.673],[0,0]],"o":[[0,0],[-10.932,4.732],[11.897,22.824],[75.614,-46.536],[0,0]],"v":[[77.17,-13.132],[-70.555,17.203],[-76.729,44.143],[-22.387,68.094],[77.98,14.108]],"c":false}]},{"i":{"x":0.833,"y":0.833},"o":{"x":0.333,"y":0},"t":34,"s":[{"i":[[0,0],[50.593,10.883],[1.207,-7.767],[-16.333,-1.59],[0,0]],"o":[[0,0],[-9.385,-2.019],[-2.555,16.443],[71.214,6.933],[0,0]],"v":[[77.17,-13.132],[-59.216,-39.574],[-75.593,-28.355],[-50.61,5.856],[77.98,14.108]],"c":false}]},{"i":{"x":0.667,"y":1},"o":{"x":0.167,"y":0.167},"t":37,"s":[{"i":[[0,0],[49.301,15.906],[2.364,-9.715],[-16.2,-2.716],[0,0]],"o":[[0,0],[-9.145,-2.95],[-5.004,20.567],[70.637,11.842],[0,0]],"v":[[77.17,-13.132],[-56.133,-10.273],[-74.274,3.117],[-54.196,47.238],[77.98,14.108]],"c":false}]},{"i":{"x":0.833,"y":0.833},"o":{"x":0.333,"y":0},"t":42,"s":[{"i":[[0,0],[35.382,-37.766],[-6.036,-5.034],[-9.773,13.182],[0,0]],"o":[[0,0],[-6.563,7.005],[12.78,10.657],[42.614,-57.477],[0,0]],"v":[[77.17,-13.132],[-31.872,83.202],[-30.689,103.017],[11.504,99.218],[77.73,25.358]],"c":false}]},{"i":{"x":0.667,"y":1},"o":{"x":0.167,"y":0.167},"t":46,"s":[{"i":[[0,0],[58.934,-25.51],[-5.619,-10.781],[-17.342,10.673],[0,0]],"o":[[0,0],[-10.932,4.732],[11.897,22.824],[75.614,-46.536],[0,0]],"v":[[77.17,-13.132],[-70.555,17.203],[-76.729,44.143],[-22.387,68.094],[77.98,14.108]],"c":false}]},{"i":{"x":0.833,"y":0.833},"o":{"x":0.333,"y":0},"t":50,"s":[{"i":[[0,0],[50.593,10.883],[1.207,-7.767],[-16.333,-1.59],[0,0]],"o":[[0,0],[-9.385,-2.019],[-2.555,16.443],[71.214,6.933],[0,0]],"v":[[77.17,-13.132],[-59.216,-39.574],[-75.593,-28.355],[-50.61,5.856],[77.98,14.108]],"c":false}]},{"i":{"x":0.667,"y":1},"o":{"x":0.167,"y":0.167},"t":53,"s":[{"i":[[0,0],[49.301,15.906],[2.364,-9.715],[-16.2,-2.716],[0,0]],"o":[[0,0],[-9.145,-2.95],[-5.004,20.567],[70.637,11.842],[0,0]],"v":[[77.17,-13.132],[-56.133,-10.273],[-74.274,3.117],[-54.196,47.238],[77.98,14.108]],"c":false}]},{"i":{"x":0.833,"y":0.833},"o":{"x":0.333,"y":0},"t":58,"s":[{"i":[[0,0],[35.382,-37.766],[-6.036,-5.034],[-9.773,13.182],[0,0]],"o":[[0,0],[-6.563,7.005],[12.78,10.657],[42.614,-57.477],[0,0]],"v":[[77.17,-13.132],[-31.872,83.202],[-30.689,103.017],[11.504,99.218],[77.73,25.358]],"c":false}]},{"i":{"x":0.667,"y":1},"o":{"x":0.167,"y":0.167},"t":62,"s":[{"i":[[0,0],[58.934,-25.51],[-5.619,-10.781],[-17.342,10.673],[0,0]],"o":[[0,0],[-10.932,4.732],[11.897,22.824],[75.614,-46.536],[0,0]],"v":[[77.17,-13.132],[-70.555,17.203],[-76.729,44.143],[-22.387,68.094],[77.98,14.108]],"c":false}]},{"i":{"x":0.833,"y":0.833},"o":{"x":0.333,"y":0},"t":66,"s":[{"i":[[0,0],[50.593,10.883],[1.207,-7.767],[-16.333,-1.59],[0,0]],"o":[[0,0],[-9.385,-2.019],[-2.555,16.443],[71.214,6.933],[0,0]],"v":[[77.17,-13.132],[-59.216,-39.574],[-75.593,-28.355],[-50.61,5.856],[77.98,14.108]],"c":false}]},{"i":{"x":0.667,"y":1},"o":{"x":0.167,"y":0.167},"t":69,"s":[{"i":[[0,0],[49.301,15.906],[2.364,-9.715],[-16.2,-2.716],[0,0]],"o":[[0,0],[-9.145,-2.95],[-5.004,20.567],[70.637,11.842],[0,0]],"v":[[77.17,-13.132],[-56.133,-10.273],[-74.274,3.117],[-54.196,47.238],[77.98,14.108]],"c":false}]},{"i":{"x":0.833,"y":0.833},"o":{"x":0.333,"y":0},"t":74,"s":[{"i":[[0,0],[35.382,-37.766],[-6.036,-5.034],[-9.773,13.182],[0,0]],"o":[[0,0],[-6.563,7.005],[12.78,10.657],[42.614,-57.477],[0,0]],"v":[[77.17,-13.132],[-31.872,83.202],[-30.689,103.017],[11.504,99.218],[77.73,25.358]],"c":false}]},{"i":{"x":0.667,"y":1},"o":{"x":0.167,"y":0.167},"t":78,"s":[{"i":[[0,0],[58.934,-25.51],[-5.619,-10.781],[-17.342,10.673],[0,0]],"o":[[0,0],[-10.932,4.732],[11.897,22.824],[75.614,-46.536],[0,0]],"v":[[77.17,-13.132],[-70.555,17.203],[-76.729,44.143],[-22.387,68.094],[77.98,14.108]],"c":false}]},{"i":{"x":0.833,"y":0.833},"o":{"x":0.333,"y":0},"t":82,"s":[{"i":[[0,0],[50.593,10.883],[1.207,-7.767],[-16.333,-1.59],[0,0]],"o":[[0,0],[-9.385,-2.019],[-2.555,16.443],[71.214,6.933],[0,0]],"v":[[77.17,-13.132],[-59.216,-39.574],[-75.593,-28.355],[-50.61,5.856],[77.98,14.108]],"c":false}]},{"i":{"x":0.667,"y":1},"o":{"x":0.167,"y":0.167},"t":85,"s":[{"i":[[0,0],[49.301,15.906],[2.364,-9.715],[-16.2,-2.716],[0,0]],"o":[[0,0],[-9.145,-2.95],[-5.004,20.567],[70.637,11.842],[0,0]],"v":[[77.17,-13.132],[-56.133,-10.273],[-74.274,3.117],[-54.196,47.238],[77.98,14.108]],"c":false}]},{"i":{"x":0.833,"y":0.833},"o":{"x":0.333,"y":0},"t":90,"s":[{"i":[[0,0],[35.382,-37.766],[-6.036,-5.034],[-9.773,13.182],[0,0]],"o":[[0,0],[-6.563,7.005],[12.78,10.657],[42.614,-57.477],[0,0]],"v":[[77.17,-13.132],[-31.872,83.202],[-30.689,103.017],[11.504,99.218],[77.73,25.358]],"c":false}]},{"i":{"x":0.667,"y":1},"o":{"x":0.167,"y":0.167},"t":94,"s":[{"i":[[0,0],[58.934,-25.51],[-5.619,-10.781],[-17.342,10.673],[0,0]],"o":[[0,0],[-10.932,4.732],[11.897,22.824],[75.614,-46.536],[0,0]],"v":[[77.17,-13.132],[-70.555,17.203],[-76.729,44.143],[-22.387,68.094],[77.98,14.108]],"c":false}]},{"i":{"x":0.833,"y":0.833},"o":{"x":0.333,"y":0},"t":98,"s":[{"i":[[0,0],[50.593,10.883],[1.207,-7.767],[-16.333,-1.59],[0,0]],"o":[[0,0],[-9.385,-2.019],[-2.555,16.443],[71.214,6.933],[0,0]],"v":[[77.17,-13.132],[-59.216,-39.574],[-75.593,-28.355],[-50.61,5.856],[77.98,14.108]],"c":false}]},{"i":{"x":0.667,"y":1},"o":{"x":0.167,"y":0.167},"t":101,"s":[{"i":[[0,0],[49.301,15.906],[2.364,-9.715],[-16.2,-2.716],[0,0]],"o":[[0,0],[-9.145,-2.95],[-5.004,20.567],[70.637,11.842],[0,0]],"v":[[77.17,-13.132],[-56.133,-10.273],[-74.274,3.117],[-54.196,47.238],[77.98,14.108]],"c":false}]},{"i":{"x":0.833,"y":0.833},"o":{"x":0.333,"y":0},"t":106,"s":[{"i":[[0,0],[35.382,-37.766],[-6.036,-5.034],[-9.773,13.182],[0,0]],"o":[[0,0],[-6.563,7.005],[12.78,10.657],[42.614,-57.477],[0,0]],"v":[[77.17,-13.132],[-31.872,83.202],[-30.689,103.017],[11.504,99.218],[77.73,25.358]],"c":false}]},{"i":{"x":0.667,"y":1},"o":{"x":0.167,"y":0.167},"t":110,"s":[{"i":[[0,0],[58.934,-25.51],[-5.619,-10.781],[-17.342,10.673],[0,0]],"o":[[0,0],[-10.932,4.732],[11.897,22.824],[75.614,-46.536],[0,0]],"v":[[77.17,-13.132],[-70.555,17.203],[-76.729,44.143],[-22.387,68.094],[77.98,14.108]],"c":false}]},{"i":{"x":0.833,"y":0.833},"o":{"x":0.333,"y":0},"t":114,"s":[{"i":[[0,0],[50.593,10.883],[1.207,-7.767],[-16.333,-1.59],[0,0]],"o":[[0,0],[-9.385,-2.019],[-2.555,16.443],[71.214,6.933],[0,0]],"v":[[77.17,-13.132],[-59.216,-39.574],[-75.593,-28.355],[-50.61,5.856],[77.98,14.108]],"c":false}]},{"i":{"x":0.667,"y":1},"o":{"x":0.167,"y":0.167},"t":117,"s":[{"i":[[0,0],[49.301,15.906],[2.364,-9.715],[-16.2,-2.716],[0,0]],"o":[[0,0],[-9.145,-2.95],[-5.004,20.567],[70.637,11.842],[0,0]],"v":[[77.17,-13.132],[-56.133,-10.273],[-74.274,3.117],[-54.196,47.238],[77.98,14.108]],"c":false}]},{"i":{"x":0.833,"y":0.833},"o":{"x":0.333,"y":0},"t":122,"s":[{"i":[[0,0],[35.382,-37.766],[-6.036,-5.034],[-9.773,13.182],[0,0]],"o":[[0,0],[-6.563,7.005],[12.78,10.657],[42.614,-57.477],[0,0]],"v":[[77.17,-13.132],[-31.872,83.202],[-30.689,103.017],[11.504,99.218],[77.73,25.358]],"c":false}]},{"i":{"x":0.667,"y":1},"o":{"x":0.167,"y":0.167},"t":126,"s":[{"i":[[0,0],[58.934,-25.51],[-5.619,-10.781],[-17.342,10.673],[0,0]],"o":[[0,0],[-10.932,4.732],[11.897,22.824],[75.614,-46.536],[0,0]],"v":[[77.17,-13.132],[-70.555,17.203],[-76.729,44.143],[-22.387,68.094],[77.98,14.108]],"c":false}]},{"i":{"x":0.833,"y":0.833},"o":{"x":0.333,"y":0},"t":130,"s":[{"i":[[0,0],[50.593,10.883],[1.207,-7.767],[-16.333,-1.59],[0,0]],"o":[[0,0],[-9.385,-2.019],[-2.555,16.443],[71.214,6.933],[0,0]],"v":[[77.17,-13.132],[-59.216,-39.574],[-75.593,-28.355],[-50.61,5.856],[77.98,14.108]],"c":false}]},{"i":{"x":0.667,"y":1},"o":{"x":0.167,"y":0.167},"t":133,"s":[{"i":[[0,0],[49.301,15.906],[2.364,-9.715],[-16.2,-2.716],[0,0]],"o":[[0,0],[-9.145,-2.95],[-5.004,20.567],[70.637,11.842],[0,0]],"v":[[77.17,-13.132],[-56.133,-10.273],[-74.274,3.117],[-54.196,47.238],[77.98,14.108]],"c":false}]},{"i":{"x":0.833,"y":0.833},"o":{"x":0.333,"y":0},"t":138,"s":[{"i":[[0,0],[35.382,-37.766],[-6.036,-5.034],[-9.773,13.182],[0,0]],"o":[[0,0],[-6.563,7.005],[12.78,10.657],[42.614,-57.477],[0,0]],"v":[[77.17,-13.132],[-31.872,83.202],[-30.689,103.017],[11.504,99.218],[77.73,25.358]],"c":false}]},{"i":{"x":0.667,"y":1},"o":{"x":0.167,"y":0.167},"t":142,"s":[{"i":[[0,0],[58.934,-25.51],[-5.619,-10.781],[-17.342,10.673],[0,0]],"o":[[0,0],[-10.932,4.732],[11.897,22.824],[75.614,-46.536],[0,0]],"v":[[77.17,-13.132],[-70.555,17.203],[-76.729,44.143],[-22.387,68.094],[77.98,14.108]],"c":false}]},{"i":{"x":0.833,"y":0.833},"o":{"x":0.333,"y":0},"t":146,"s":[{"i":[[0,0],[50.593,10.883],[1.207,-7.767],[-16.333,-1.59],[0,0]],"o":[[0,0],[-9.385,-2.019],[-2.555,16.443],[71.214,6.933],[0,0]],"v":[[77.17,-13.132],[-59.216,-39.574],[-75.593,-28.355],[-50.61,5.856],[77.98,14.108]],"c":false}]},{"i":{"x":0.667,"y":1},"o":{"x":0.167,"y":0.167},"t":149,"s":[{"i":[[0,0],[49.301,15.906],[2.364,-9.715],[-16.2,-2.716],[0,0]],"o":[[0,0],[-9.145,-2.95],[-5.004,20.567],[70.637,11.842],[0,0]],"v":[[77.17,-13.132],[-56.133,-10.273],[-74.274,3.117],[-54.196,47.238],[77.98,14.108]],"c":false}]},{"i":{"x":0.833,"y":0.833},"o":{"x":0.333,"y":0},"t":154,"s":[{"i":[[0,0],[35.382,-37.766],[-6.036,-5.034],[-9.773,13.182],[0,0]],"o":[[0,0],[-6.563,7.005],[12.78,10.657],[42.614,-57.477],[0,0]],"v":[[77.17,-13.132],[-31.872,83.202],[-30.689,103.017],[11.504,99.218],[77.73,25.358]],"c":false}]},{"i":{"x":0.667,"y":1},"o":{"x":0.167,"y":0.167},"t":158,"s":[{"i":[[0,0],[58.934,-25.51],[-5.619,-10.781],[-17.342,10.673],[0,0]],"o":[[0,0],[-10.932,4.732],[11.897,22.824],[75.614,-46.536],[0,0]],"v":[[77.17,-13.132],[-70.555,17.203],[-76.729,44.143],[-22.387,68.094],[77.98,14.108]],"c":false}]},{"i":{"x":0.11,"y":1},"o":{"x":0.333,"y":0},"t":162,"s":[{"i":[[0,0],[50.593,10.883],[1.207,-7.767],[-16.333,-1.59],[0,0]],"o":[[0,0],[-9.385,-2.019],[-2.555,16.443],[71.214,6.933],[0,0]],"v":[[77.17,-13.132],[-59.216,-39.574],[-75.593,-28.355],[-50.61,5.856],[77.98,14.108]],"c":false}]},{"t":180,"s":[{"i":[[0,0],[51.664,2.986],[0,-7.86],[-16.383,0.937],[0,0]],"o":[[0,0],[-9.583,-0.554],[0,16.64],[71.434,-4.084],[0,0]],"v":[[77.17,-13.132],[-63.52,-21.772],[-77.98,-8.172],[-48.04,21.798],[77.98,14.108]],"c":false}]}],"ix":2},"nm":"Path 1","mn":"ADBE Vector Shape - Group","hd":false},{"ty":"st","c":{"a":0,"k":[0.031372550875,0.639215707779,0.521568655968,1],"ix":3,"x":"var $bm_rt;\n$bm_rt = thisComp.layer('Color  & Stroke Change').effect('Primary')('Color');"},"o":{"a":0,"k":100,"ix":4},"w":{"a":0,"k":12,"ix":5,"x":"var $bm_rt;\n$bm_rt = $bm_mul(17.2 \/ 100, thisComp.layer('Color  & Stroke Change').effect('Stroke')('Slider'));"},"lc":2,"lj":2,"bm":0,"nm":"Stroke 1","mn":"ADBE Vector Graphic - Stroke","hd":false},{"ty":"tr","p":{"a":0,"k":[0,0],"ix":2},"a":{"a":0,"k":[0,0],"ix":1},"s":{"a":0,"k":[100,100],"ix":3},"r":{"a":0,"k":0,"ix":6},"o":{"a":0,"k":100,"ix":7},"sk":{"a":0,"k":0,"ix":4},"sa":{"a":0,"k":0,"ix":5},"nm":"Transform"}],"nm":"Group 1","np":2,"cix":2,"bm":0,"ix":1,"mn":"ADBE Vector Group","hd":false}],"ip":0,"op":844,"st":0,"bm":0},{"ddd":0,"ind":8,"ty":4,"nm":"outline 4","parent":5,"sr":1,"ks":{"o":{"a":0,"k":100,"ix":11},"r":{"a":0,"k":0,"ix":10},"p":{"a":0,"k":[162.667,235.559,0],"ix":2,"l":2},"a":{"a":0,"k":[0,0,0],"ix":1,"l":2},"s":{"a":0,"k":[100,100,100],"ix":6,"l":2}},"ao":0,"shapes":[{"ty":"gr","it":[{"ind":0,"ty":"sh","ix":1,"ks":{"a":1,"k":[{"i":{"x":0.667,"y":1},"o":{"x":0.333,"y":0},"t":0,"s":[{"i":[[0,0],[41.104,-13.734],[3.18,0],[3.64,13.42],[-8.612,1.808],[0,0],[0,0],[0,0]],"o":[[0,0],[-3.076,1.028],[-13.14,0],[-2.05,-7.58],[53.734,-11.284],[0,0],[0,0],[0,0]],"v":[[72.519,-4.425],[-33.521,31.425],[-43.121,33.015],[-72.041,10.875],[-61.651,-6.025],[69.239,-33.015],[69.249,-33.015],[69.269,-33.015]],"c":false}]},{"i":{"x":0.833,"y":0.833},"o":{"x":0.333,"y":0},"t":4,"s":[{"i":[[0,0],[43.293,-1.964],[3.059,0.87],[-0.181,13.904],[-8.778,-0.617],[0,0],[0,0],[0,0]],"o":[[0,0],[-3.24,0.147],[-12.639,-3.595],[0.102,-7.852],[54.771,3.848],[0,0],[0,0],[0,0]],"v":[[72.519,-4.425],[-47.96,2.453],[-57.629,1.355],[-79.388,-27.852],[-64.771,-41.265],[69.239,-33.015],[69.249,-33.015],[69.269,-33.015]],"c":false}]},{"i":{"x":0.667,"y":1},"o":{"x":0.167,"y":0.167},"t":8,"s":[{"i":[[0,0],[42.477,-14.805],[3.169,0.263],[2.138,18.097],[-8.781,1.684],[0,0],[0,0],[0,0]],"o":[[0,0],[-3.179,1.108],[-13.095,-1.089],[-1.207,-10.221],[54.793,-10.51],[0,0],[0,0],[0,0]],"v":[[72.019,0.075],[-11.619,69.586],[-21.361,70.899],[-47.741,39.146],[-35.524,17.599],[68.739,-28.515],[68.749,-28.515],[68.769,-28.515]],"c":false}]},{"i":{"x":0.833,"y":0.833},"o":{"x":0.333,"y":0},"t":12,"s":[{"i":[[0,0],[28.478,-32.668],[2.742,-1.611],[9.931,9.733],[-6.508,5.922],[0,0],[0,0],[0,0]],"o":[[0,0],[-2.131,2.445],[-11.328,6.658],[-5.608,-5.496],[40.608,-36.955],[0,0],[0,0],[0,0]],"v":[[72.519,5.325],[0.826,63.342],[-6.645,69.577],[-42.796,65.143],[-42.401,45.309],[71.739,-25.015],[71.749,-25.015],[71.769,-25.015]],"c":false}]},{"i":{"x":0.667,"y":1},"o":{"x":0.167,"y":0.167},"t":16,"s":[{"i":[[0,0],[42.477,-14.805],[3.169,0.263],[2.138,18.097],[-8.781,1.684],[0,0],[0,0],[0,0]],"o":[[0,0],[-3.179,1.108],[-13.095,-1.089],[-1.207,-10.221],[54.793,-10.51],[0,0],[0,0],[0,0]],"v":[[72.519,-0.925],[-30.619,42.086],[-40.361,43.399],[-66.741,11.646],[-54.524,-9.901],[69.239,-29.515],[69.249,-29.515],[69.269,-29.515]],"c":false}]},{"i":{"x":0.833,"y":0.833},"o":{"x":0.333,"y":0},"t":20,"s":[{"i":[[0,0],[43.293,-1.964],[3.059,0.87],[-0.181,13.904],[-8.778,-0.617],[0,0],[0,0],[0,0]],"o":[[0,0],[-3.24,0.147],[-12.639,-3.595],[0.102,-7.852],[54.771,3.848],[0,0],[0,0],[0,0]],"v":[[72.519,-4.425],[-47.96,2.453],[-57.629,1.355],[-79.388,-27.852],[-64.771,-41.265],[69.239,-33.015],[69.249,-33.015],[69.269,-33.015]],"c":false}]},{"i":{"x":0.667,"y":1},"o":{"x":0.167,"y":0.167},"t":24,"s":[{"i":[[0,0],[42.477,-14.805],[3.169,0.263],[2.138,18.097],[-8.781,1.684],[0,0],[0,0],[0,0]],"o":[[0,0],[-3.179,1.108],[-13.095,-1.089],[-1.207,-10.221],[54.793,-10.51],[0,0],[0,0],[0,0]],"v":[[72.019,0.075],[-11.619,69.586],[-21.361,70.899],[-47.741,39.146],[-35.524,17.599],[68.739,-28.515],[68.749,-28.515],[68.769,-28.515]],"c":false}]},{"i":{"x":0.833,"y":0.833},"o":{"x":0.333,"y":0},"t":28,"s":[{"i":[[0,0],[28.478,-32.668],[2.742,-1.611],[9.931,9.733],[-6.508,5.922],[0,0],[0,0],[0,0]],"o":[[0,0],[-2.131,2.445],[-11.328,6.658],[-5.608,-5.496],[40.608,-36.955],[0,0],[0,0],[0,0]],"v":[[72.519,5.325],[0.826,63.342],[-6.645,69.577],[-42.796,65.143],[-42.401,45.309],[71.739,-25.015],[71.749,-25.015],[71.769,-25.015]],"c":false}]},{"i":{"x":0.667,"y":1},"o":{"x":0.167,"y":0.167},"t":32,"s":[{"i":[[0,0],[42.477,-14.805],[3.169,0.263],[2.138,18.097],[-8.781,1.684],[0,0],[0,0],[0,0]],"o":[[0,0],[-3.179,1.108],[-13.095,-1.089],[-1.207,-10.221],[54.793,-10.51],[0,0],[0,0],[0,0]],"v":[[72.519,-0.925],[-30.619,42.086],[-40.361,43.399],[-66.741,11.646],[-54.524,-9.901],[69.239,-29.515],[69.249,-29.515],[69.269,-29.515]],"c":false}]},{"i":{"x":0.833,"y":0.833},"o":{"x":0.333,"y":0},"t":36,"s":[{"i":[[0,0],[43.293,-1.964],[3.059,0.87],[-0.181,13.904],[-8.778,-0.617],[0,0],[0,0],[0,0]],"o":[[0,0],[-3.24,0.147],[-12.639,-3.595],[0.102,-7.852],[54.771,3.848],[0,0],[0,0],[0,0]],"v":[[72.519,-4.425],[-47.96,2.453],[-57.629,1.355],[-79.388,-27.852],[-64.771,-41.265],[69.239,-33.015],[69.249,-33.015],[69.269,-33.015]],"c":false}]},{"i":{"x":0.667,"y":1},"o":{"x":0.167,"y":0.167},"t":40,"s":[{"i":[[0,0],[42.477,-14.805],[3.169,0.263],[2.138,18.097],[-8.781,1.684],[0,0],[0,0],[0,0]],"o":[[0,0],[-3.179,1.108],[-13.095,-1.089],[-1.207,-10.221],[54.793,-10.51],[0,0],[0,0],[0,0]],"v":[[72.019,0.075],[-11.619,69.586],[-21.361,70.899],[-47.741,39.146],[-35.524,17.599],[68.739,-28.515],[68.749,-28.515],[68.769,-28.515]],"c":false}]},{"i":{"x":0.833,"y":0.833},"o":{"x":0.333,"y":0},"t":44,"s":[{"i":[[0,0],[28.478,-32.668],[2.742,-1.611],[9.931,9.733],[-6.508,5.922],[0,0],[0,0],[0,0]],"o":[[0,0],[-2.131,2.445],[-11.328,6.658],[-5.608,-5.496],[40.608,-36.955],[0,0],[0,0],[0,0]],"v":[[72.519,5.325],[0.826,63.342],[-6.645,69.577],[-42.796,65.143],[-42.401,45.309],[71.739,-25.015],[71.749,-25.015],[71.769,-25.015]],"c":false}]},{"i":{"x":0.667,"y":1},"o":{"x":0.167,"y":0.167},"t":48,"s":[{"i":[[0,0],[42.477,-14.805],[3.169,0.263],[2.138,18.097],[-8.781,1.684],[0,0],[0,0],[0,0]],"o":[[0,0],[-3.179,1.108],[-13.095,-1.089],[-1.207,-10.221],[54.793,-10.51],[0,0],[0,0],[0,0]],"v":[[72.519,-0.925],[-30.619,42.086],[-40.361,43.399],[-66.741,11.646],[-54.524,-9.901],[69.239,-29.515],[69.249,-29.515],[69.269,-29.515]],"c":false}]},{"i":{"x":0.833,"y":0.833},"o":{"x":0.333,"y":0},"t":52,"s":[{"i":[[0,0],[43.293,-1.964],[3.059,0.87],[-0.181,13.904],[-8.778,-0.617],[0,0],[0,0],[0,0]],"o":[[0,0],[-3.24,0.147],[-12.639,-3.595],[0.102,-7.852],[54.771,3.848],[0,0],[0,0],[0,0]],"v":[[72.519,-4.425],[-47.96,2.453],[-57.629,1.355],[-79.388,-27.852],[-64.771,-41.265],[69.239,-33.015],[69.249,-33.015],[69.269,-33.015]],"c":false}]},{"i":{"x":0.667,"y":1},"o":{"x":0.167,"y":0.167},"t":56,"s":[{"i":[[0,0],[42.477,-14.805],[3.169,0.263],[2.138,18.097],[-8.781,1.684],[0,0],[0,0],[0,0]],"o":[[0,0],[-3.179,1.108],[-13.095,-1.089],[-1.207,-10.221],[54.793,-10.51],[0,0],[0,0],[0,0]],"v":[[72.019,0.075],[-11.619,69.586],[-21.361,70.899],[-47.741,39.146],[-35.524,17.599],[68.739,-28.515],[68.749,-28.515],[68.769,-28.515]],"c":false}]},{"i":{"x":0.833,"y":0.833},"o":{"x":0.333,"y":0},"t":60,"s":[{"i":[[0,0],[28.478,-32.668],[2.742,-1.611],[9.931,9.733],[-6.508,5.922],[0,0],[0,0],[0,0]],"o":[[0,0],[-2.131,2.445],[-11.328,6.658],[-5.608,-5.496],[40.608,-36.955],[0,0],[0,0],[0,0]],"v":[[72.519,5.325],[0.826,63.342],[-6.645,69.577],[-42.796,65.143],[-42.401,45.309],[71.739,-25.015],[71.749,-25.015],[71.769,-25.015]],"c":false}]},{"i":{"x":0.667,"y":1},"o":{"x":0.167,"y":0.167},"t":64,"s":[{"i":[[0,0],[42.477,-14.805],[3.169,0.263],[2.138,18.097],[-8.781,1.684],[0,0],[0,0],[0,0]],"o":[[0,0],[-3.179,1.108],[-13.095,-1.089],[-1.207,-10.221],[54.793,-10.51],[0,0],[0,0],[0,0]],"v":[[72.519,-0.925],[-30.619,42.086],[-40.361,43.399],[-66.741,11.646],[-54.524,-9.901],[69.239,-29.515],[69.249,-29.515],[69.269,-29.515]],"c":false}]},{"i":{"x":0.833,"y":0.833},"o":{"x":0.333,"y":0},"t":68,"s":[{"i":[[0,0],[43.293,-1.964],[3.059,0.87],[-0.181,13.904],[-8.778,-0.617],[0,0],[0,0],[0,0]],"o":[[0,0],[-3.24,0.147],[-12.639,-3.595],[0.102,-7.852],[54.771,3.848],[0,0],[0,0],[0,0]],"v":[[72.519,-4.425],[-47.96,2.453],[-57.629,1.355],[-79.388,-27.852],[-64.771,-41.265],[69.239,-33.015],[69.249,-33.015],[69.269,-33.015]],"c":false}]},{"i":{"x":0.667,"y":1},"o":{"x":0.167,"y":0.167},"t":72,"s":[{"i":[[0,0],[42.477,-14.805],[3.169,0.263],[2.138,18.097],[-8.781,1.684],[0,0],[0,0],[0,0]],"o":[[0,0],[-3.179,1.108],[-13.095,-1.089],[-1.207,-10.221],[54.793,-10.51],[0,0],[0,0],[0,0]],"v":[[72.019,0.075],[-11.619,69.586],[-21.361,70.899],[-47.741,39.146],[-35.524,17.599],[68.739,-28.515],[68.749,-28.515],[68.769,-28.515]],"c":false}]},{"i":{"x":0.833,"y":0.833},"o":{"x":0.333,"y":0},"t":76,"s":[{"i":[[0,0],[28.478,-32.668],[2.742,-1.611],[9.931,9.733],[-6.508,5.922],[0,0],[0,0],[0,0]],"o":[[0,0],[-2.131,2.445],[-11.328,6.658],[-5.608,-5.496],[40.608,-36.955],[0,0],[0,0],[0,0]],"v":[[72.519,5.325],[0.826,63.342],[-6.645,69.577],[-42.796,65.143],[-42.401,45.309],[71.739,-25.015],[71.749,-25.015],[71.769,-25.015]],"c":false}]},{"i":{"x":0.667,"y":1},"o":{"x":0.167,"y":0.167},"t":80,"s":[{"i":[[0,0],[42.477,-14.805],[3.169,0.263],[2.138,18.097],[-8.781,1.684],[0,0],[0,0],[0,0]],"o":[[0,0],[-3.179,1.108],[-13.095,-1.089],[-1.207,-10.221],[54.793,-10.51],[0,0],[0,0],[0,0]],"v":[[72.519,-0.925],[-30.619,42.086],[-40.361,43.399],[-66.741,11.646],[-54.524,-9.901],[69.239,-29.515],[69.249,-29.515],[69.269,-29.515]],"c":false}]},{"i":{"x":0.833,"y":0.833},"o":{"x":0.333,"y":0},"t":84,"s":[{"i":[[0,0],[43.293,-1.964],[3.059,0.87],[-0.181,13.904],[-8.778,-0.617],[0,0],[0,0],[0,0]],"o":[[0,0],[-3.24,0.147],[-12.639,-3.595],[0.102,-7.852],[54.771,3.848],[0,0],[0,0],[0,0]],"v":[[72.519,-4.425],[-47.96,2.453],[-57.629,1.355],[-79.388,-27.852],[-64.771,-41.265],[69.239,-33.015],[69.249,-33.015],[69.269,-33.015]],"c":false}]},{"i":{"x":0.667,"y":1},"o":{"x":0.167,"y":0.167},"t":88,"s":[{"i":[[0,0],[42.477,-14.805],[3.169,0.263],[2.138,18.097],[-8.781,1.684],[0,0],[0,0],[0,0]],"o":[[0,0],[-3.179,1.108],[-13.095,-1.089],[-1.207,-10.221],[54.793,-10.51],[0,0],[0,0],[0,0]],"v":[[72.019,0.075],[-11.619,69.586],[-21.361,70.899],[-47.741,39.146],[-35.524,17.599],[68.739,-28.515],[68.749,-28.515],[68.769,-28.515]],"c":false}]},{"i":{"x":0.833,"y":0.833},"o":{"x":0.333,"y":0},"t":92,"s":[{"i":[[0,0],[28.478,-32.668],[2.742,-1.611],[9.931,9.733],[-6.508,5.922],[0,0],[0,0],[0,0]],"o":[[0,0],[-2.131,2.445],[-11.328,6.658],[-5.608,-5.496],[40.608,-36.955],[0,0],[0,0],[0,0]],"v":[[72.519,5.325],[0.826,63.342],[-6.645,69.577],[-42.796,65.143],[-42.401,45.309],[71.739,-25.015],[71.749,-25.015],[71.769,-25.015]],"c":false}]},{"i":{"x":0.667,"y":1},"o":{"x":0.167,"y":0.167},"t":96,"s":[{"i":[[0,0],[42.477,-14.805],[3.169,0.263],[2.138,18.097],[-8.781,1.684],[0,0],[0,0],[0,0]],"o":[[0,0],[-3.179,1.108],[-13.095,-1.089],[-1.207,-10.221],[54.793,-10.51],[0,0],[0,0],[0,0]],"v":[[72.519,-0.925],[-30.619,42.086],[-40.361,43.399],[-66.741,11.646],[-54.524,-9.901],[69.239,-29.515],[69.249,-29.515],[69.269,-29.515]],"c":false}]},{"i":{"x":0.833,"y":0.833},"o":{"x":0.333,"y":0},"t":100,"s":[{"i":[[0,0],[43.293,-1.964],[3.059,0.87],[-0.181,13.904],[-8.778,-0.617],[0,0],[0,0],[0,0]],"o":[[0,0],[-3.24,0.147],[-12.639,-3.595],[0.102,-7.852],[54.771,3.848],[0,0],[0,0],[0,0]],"v":[[72.519,-4.425],[-47.96,2.453],[-57.629,1.355],[-79.388,-27.852],[-64.771,-41.265],[69.239,-33.015],[69.249,-33.015],[69.269,-33.015]],"c":false}]},{"i":{"x":0.667,"y":1},"o":{"x":0.167,"y":0.167},"t":104,"s":[{"i":[[0,0],[42.477,-14.805],[3.169,0.263],[2.138,18.097],[-8.781,1.684],[0,0],[0,0],[0,0]],"o":[[0,0],[-3.179,1.108],[-13.095,-1.089],[-1.207,-10.221],[54.793,-10.51],[0,0],[0,0],[0,0]],"v":[[72.019,0.075],[-11.619,69.586],[-21.361,70.899],[-47.741,39.146],[-35.524,17.599],[68.739,-28.515],[68.749,-28.515],[68.769,-28.515]],"c":false}]},{"i":{"x":0.833,"y":0.833},"o":{"x":0.333,"y":0},"t":108,"s":[{"i":[[0,0],[28.478,-32.668],[2.742,-1.611],[9.931,9.733],[-6.508,5.922],[0,0],[0,0],[0,0]],"o":[[0,0],[-2.131,2.445],[-11.328,6.658],[-5.608,-5.496],[40.608,-36.955],[0,0],[0,0],[0,0]],"v":[[72.519,5.325],[0.826,63.342],[-6.645,69.577],[-42.796,65.143],[-42.401,45.309],[71.739,-25.015],[71.749,-25.015],[71.769,-25.015]],"c":false}]},{"i":{"x":0.667,"y":1},"o":{"x":0.167,"y":0.167},"t":112,"s":[{"i":[[0,0],[42.477,-14.805],[3.169,0.263],[2.138,18.097],[-8.781,1.684],[0,0],[0,0],[0,0]],"o":[[0,0],[-3.179,1.108],[-13.095,-1.089],[-1.207,-10.221],[54.793,-10.51],[0,0],[0,0],[0,0]],"v":[[72.519,-0.925],[-30.619,42.086],[-40.361,43.399],[-66.741,11.646],[-54.524,-9.901],[69.239,-29.515],[69.249,-29.515],[69.269,-29.515]],"c":false}]},{"i":{"x":0.833,"y":0.833},"o":{"x":0.333,"y":0},"t":116,"s":[{"i":[[0,0],[43.293,-1.964],[3.059,0.87],[-0.181,13.904],[-8.778,-0.617],[0,0],[0,0],[0,0]],"o":[[0,0],[-3.24,0.147],[-12.639,-3.595],[0.102,-7.852],[54.771,3.848],[0,0],[0,0],[0,0]],"v":[[72.519,-4.425],[-47.96,2.453],[-57.629,1.355],[-79.388,-27.852],[-64.771,-41.265],[69.239,-33.015],[69.249,-33.015],[69.269,-33.015]],"c":false}]},{"i":{"x":0.667,"y":1},"o":{"x":0.167,"y":0.167},"t":120,"s":[{"i":[[0,0],[42.477,-14.805],[3.169,0.263],[2.138,18.097],[-8.781,1.684],[0,0],[0,0],[0,0]],"o":[[0,0],[-3.179,1.108],[-13.095,-1.089],[-1.207,-10.221],[54.793,-10.51],[0,0],[0,0],[0,0]],"v":[[72.019,0.075],[-11.619,69.586],[-21.361,70.899],[-47.741,39.146],[-35.524,17.599],[68.739,-28.515],[68.749,-28.515],[68.769,-28.515]],"c":false}]},{"i":{"x":0.833,"y":0.833},"o":{"x":0.333,"y":0},"t":124,"s":[{"i":[[0,0],[28.478,-32.668],[2.742,-1.611],[9.931,9.733],[-6.508,5.922],[0,0],[0,0],[0,0]],"o":[[0,0],[-2.131,2.445],[-11.328,6.658],[-5.608,-5.496],[40.608,-36.955],[0,0],[0,0],[0,0]],"v":[[72.519,5.325],[0.826,63.342],[-6.645,69.577],[-42.796,65.143],[-42.401,45.309],[71.739,-25.015],[71.749,-25.015],[71.769,-25.015]],"c":false}]},{"i":{"x":0.667,"y":1},"o":{"x":0.167,"y":0.167},"t":128,"s":[{"i":[[0,0],[42.477,-14.805],[3.169,0.263],[2.138,18.097],[-8.781,1.684],[0,0],[0,0],[0,0]],"o":[[0,0],[-3.179,1.108],[-13.095,-1.089],[-1.207,-10.221],[54.793,-10.51],[0,0],[0,0],[0,0]],"v":[[72.519,-0.925],[-30.619,42.086],[-40.361,43.399],[-66.741,11.646],[-54.524,-9.901],[69.239,-29.515],[69.249,-29.515],[69.269,-29.515]],"c":false}]},{"i":{"x":0.833,"y":0.833},"o":{"x":0.333,"y":0},"t":132,"s":[{"i":[[0,0],[43.293,-1.964],[3.059,0.87],[-0.181,13.904],[-8.778,-0.617],[0,0],[0,0],[0,0]],"o":[[0,0],[-3.24,0.147],[-12.639,-3.595],[0.102,-7.852],[54.771,3.848],[0,0],[0,0],[0,0]],"v":[[72.519,-4.425],[-47.96,2.453],[-57.629,1.355],[-79.388,-27.852],[-64.771,-41.265],[69.239,-33.015],[69.249,-33.015],[69.269,-33.015]],"c":false}]},{"i":{"x":0.667,"y":1},"o":{"x":0.167,"y":0.167},"t":136,"s":[{"i":[[0,0],[42.477,-14.805],[3.169,0.263],[2.138,18.097],[-8.781,1.684],[0,0],[0,0],[0,0]],"o":[[0,0],[-3.179,1.108],[-13.095,-1.089],[-1.207,-10.221],[54.793,-10.51],[0,0],[0,0],[0,0]],"v":[[72.019,0.075],[-11.619,69.586],[-21.361,70.899],[-47.741,39.146],[-35.524,17.599],[68.739,-28.515],[68.749,-28.515],[68.769,-28.515]],"c":false}]},{"i":{"x":0.833,"y":0.833},"o":{"x":0.333,"y":0},"t":140,"s":[{"i":[[0,0],[28.478,-32.668],[2.742,-1.611],[9.931,9.733],[-6.508,5.922],[0,0],[0,0],[0,0]],"o":[[0,0],[-2.131,2.445],[-11.328,6.658],[-5.608,-5.496],[40.608,-36.955],[0,0],[0,0],[0,0]],"v":[[72.519,5.325],[0.826,63.342],[-6.645,69.577],[-42.796,65.143],[-42.401,45.309],[71.739,-25.015],[71.749,-25.015],[71.769,-25.015]],"c":false}]},{"i":{"x":0.667,"y":1},"o":{"x":0.167,"y":0.167},"t":144,"s":[{"i":[[0,0],[42.477,-14.805],[3.169,0.263],[2.138,18.097],[-8.781,1.684],[0,0],[0,0],[0,0]],"o":[[0,0],[-3.179,1.108],[-13.095,-1.089],[-1.207,-10.221],[54.793,-10.51],[0,0],[0,0],[0,0]],"v":[[72.519,-0.925],[-30.619,42.086],[-40.361,43.399],[-66.741,11.646],[-54.524,-9.901],[69.239,-29.515],[69.249,-29.515],[69.269,-29.515]],"c":false}]},{"i":{"x":0.833,"y":0.833},"o":{"x":0.333,"y":0},"t":148,"s":[{"i":[[0,0],[43.293,-1.964],[3.059,0.87],[-0.181,13.904],[-8.778,-0.617],[0,0],[0,0],[0,0]],"o":[[0,0],[-3.24,0.147],[-12.639,-3.595],[0.102,-7.852],[54.771,3.848],[0,0],[0,0],[0,0]],"v":[[72.519,-4.425],[-47.96,2.453],[-57.629,1.355],[-79.388,-27.852],[-64.771,-41.265],[69.239,-33.015],[69.249,-33.015],[69.269,-33.015]],"c":false}]},{"i":{"x":0.667,"y":1},"o":{"x":0.167,"y":0.167},"t":152,"s":[{"i":[[0,0],[42.477,-14.805],[3.169,0.263],[2.138,18.097],[-8.781,1.684],[0,0],[0,0],[0,0]],"o":[[0,0],[-3.179,1.108],[-13.095,-1.089],[-1.207,-10.221],[54.793,-10.51],[0,0],[0,0],[0,0]],"v":[[72.019,0.075],[-11.619,69.586],[-21.361,70.899],[-47.741,39.146],[-35.524,17.599],[68.739,-28.515],[68.749,-28.515],[68.769,-28.515]],"c":false}]},{"i":{"x":0.833,"y":0.833},"o":{"x":0.333,"y":0},"t":156,"s":[{"i":[[0,0],[28.478,-32.668],[2.742,-1.611],[9.931,9.733],[-6.508,5.922],[0,0],[0,0],[0,0]],"o":[[0,0],[-2.131,2.445],[-11.328,6.658],[-5.608,-5.496],[40.608,-36.955],[0,0],[0,0],[0,0]],"v":[[72.519,5.325],[0.826,63.342],[-6.645,69.577],[-42.796,65.143],[-42.401,45.309],[71.739,-25.015],[71.749,-25.015],[71.769,-25.015]],"c":false}]},{"i":{"x":0.667,"y":1},"o":{"x":0.167,"y":0.167},"t":160,"s":[{"i":[[0,0],[42.477,-14.805],[3.169,0.263],[2.138,18.097],[-8.781,1.684],[0,0],[0,0],[0,0]],"o":[[0,0],[-3.179,1.108],[-13.095,-1.089],[-1.207,-10.221],[54.793,-10.51],[0,0],[0,0],[0,0]],"v":[[72.519,-0.925],[-30.619,42.086],[-40.361,43.399],[-66.741,11.646],[-54.524,-9.901],[69.239,-29.515],[69.249,-29.515],[69.269,-29.515]],"c":false}]},{"i":{"x":0.11,"y":1},"o":{"x":0.333,"y":0},"t":164,"s":[{"i":[[0,0],[43.293,-1.964],[3.059,0.87],[-0.181,13.904],[-8.778,-0.617],[0,0],[0,0],[0,0]],"o":[[0,0],[-3.24,0.147],[-12.639,-3.595],[0.102,-7.852],[54.771,3.848],[0,0],[0,0],[0,0]],"v":[[72.519,-4.425],[-47.96,2.453],[-57.629,1.355],[-79.388,-27.852],[-64.771,-41.265],[69.239,-33.015],[69.249,-33.015],[69.269,-33.015]],"c":false}]},{"t":180,"s":[{"i":[[0,0],[41.104,-13.734],[3.18,0],[3.64,13.42],[-8.612,1.808],[0,0],[0,0],[0,0]],"o":[[0,0],[-3.076,1.028],[-13.14,0],[-2.05,-7.58],[53.734,-11.284],[0,0],[0,0],[0,0]],"v":[[72.519,-4.425],[-33.521,31.425],[-43.121,33.015],[-72.041,10.875],[-61.651,-6.025],[69.239,-33.015],[69.249,-33.015],[69.269,-33.015]],"c":false}]}],"ix":2},"nm":"Path 1","mn":"ADBE Vector Shape - Group","hd":false},{"ty":"tm","s":{"a":0,"k":0,"ix":1},"e":{"a":1,"k":[{"i":{"x":[0.833],"y":[0.833]},"o":{"x":[0.167],"y":[0.167]},"t":0,"s":[100]},{"i":{"x":[0.833],"y":[0.833]},"o":{"x":[0.167],"y":[0.167]},"t":2,"s":[100]},{"i":{"x":[0.833],"y":[0.833]},"o":{"x":[0.167],"y":[0.167]},"t":3,"s":[59]},{"i":{"x":[0.833],"y":[0.833]},"o":{"x":[0.167],"y":[0.167]},"t":4,"s":[53]},{"i":{"x":[0.833],"y":[0.833]},"o":{"x":[0.167],"y":[0.167]},"t":5,"s":[49]},{"i":{"x":[0.833],"y":[0.833]},"o":{"x":[0.167],"y":[0.167]},"t":6,"s":[51.5]},{"i":{"x":[0.833],"y":[0.833]},"o":{"x":[0.167],"y":[0.167]},"t":8,"s":[56]},{"i":{"x":[0.833],"y":[0.833]},"o":{"x":[0.167],"y":[0.167]},"t":10,"s":[59]},{"i":{"x":[0.833],"y":[0.833]},"o":{"x":[0.167],"y":[0.167]},"t":11,"s":[54]},{"i":{"x":[0.833],"y":[0.833]},"o":{"x":[0.167],"y":[0.167]},"t":12,"s":[56]},{"i":{"x":[0.833],"y":[0.833]},"o":{"x":[0.167],"y":[0.167]},"t":13,"s":[57.5]},{"i":{"x":[0.833],"y":[0.833]},"o":{"x":[0.167],"y":[0.167]},"t":14,"s":[57]},{"i":{"x":[0.833],"y":[0.833]},"o":{"x":[0.167],"y":[0.167]},"t":15,"s":[100]},{"i":{"x":[0.833],"y":[0.833]},"o":{"x":[0.167],"y":[0.167]},"t":16,"s":[100]},{"i":{"x":[0.833],"y":[0.833]},"o":{"x":[0.167],"y":[0.167]},"t":18,"s":[100]},{"i":{"x":[0.833],"y":[0.833]},"o":{"x":[0.167],"y":[0.167]},"t":19,"s":[59]},{"i":{"x":[0.833],"y":[0.833]},"o":{"x":[0.167],"y":[0.167]},"t":20,"s":[53]},{"i":{"x":[0.833],"y":[0.833]},"o":{"x":[0.167],"y":[0.167]},"t":21,"s":[49]},{"i":{"x":[0.833],"y":[0.833]},"o":{"x":[0.167],"y":[0.167]},"t":22,"s":[51.5]},{"i":{"x":[0.833],"y":[0.833]},"o":{"x":[0.167],"y":[0.167]},"t":24,"s":[56]},{"i":{"x":[0.833],"y":[0.833]},"o":{"x":[0.167],"y":[0.167]},"t":26,"s":[59]},{"i":{"x":[0.833],"y":[0.833]},"o":{"x":[0.167],"y":[0.167]},"t":27,"s":[54]},{"i":{"x":[0.833],"y":[0.833]},"o":{"x":[0.167],"y":[0.167]},"t":28,"s":[56]},{"i":{"x":[0.833],"y":[0.833]},"o":{"x":[0.167],"y":[0.167]},"t":29,"s":[57.5]},{"i":{"x":[0.833],"y":[0.833]},"o":{"x":[0.167],"y":[0.167]},"t":30,"s":[57]},{"i":{"x":[0.833],"y":[0.833]},"o":{"x":[0.167],"y":[0.167]},"t":31,"s":[100]},{"i":{"x":[0.833],"y":[0.833]},"o":{"x":[0.167],"y":[0.167]},"t":32,"s":[100]},{"i":{"x":[0.833],"y":[0.833]},"o":{"x":[0.167],"y":[0.167]},"t":34,"s":[100]},{"i":{"x":[0.833],"y":[0.833]},"o":{"x":[0.167],"y":[0.167]},"t":35,"s":[59]},{"i":{"x":[0.833],"y":[0.833]},"o":{"x":[0.167],"y":[0.167]},"t":36,"s":[53]},{"i":{"x":[0.833],"y":[0.833]},"o":{"x":[0.167],"y":[0.167]},"t":37,"s":[49]},{"i":{"x":[0.833],"y":[0.833]},"o":{"x":[0.167],"y":[0.167]},"t":38,"s":[51.5]},{"i":{"x":[0.833],"y":[0.833]},"o":{"x":[0.167],"y":[0.167]},"t":40,"s":[56]},{"i":{"x":[0.833],"y":[0.833]},"o":{"x":[0.167],"y":[0.167]},"t":42,"s":[59]},{"i":{"x":[0.833],"y":[0.833]},"o":{"x":[0.167],"y":[0.167]},"t":43,"s":[54]},{"i":{"x":[0.833],"y":[0.833]},"o":{"x":[0.167],"y":[0.167]},"t":44,"s":[56]},{"i":{"x":[0.833],"y":[0.833]},"o":{"x":[0.167],"y":[0.167]},"t":45,"s":[57.5]},{"i":{"x":[0.833],"y":[0.833]},"o":{"x":[0.167],"y":[0.167]},"t":46,"s":[57]},{"i":{"x":[0.833],"y":[0.833]},"o":{"x":[0.167],"y":[0.167]},"t":47,"s":[100]},{"i":{"x":[0.833],"y":[0.833]},"o":{"x":[0.167],"y":[0.167]},"t":48,"s":[100]},{"i":{"x":[0.833],"y":[0.833]},"o":{"x":[0.167],"y":[0.167]},"t":50,"s":[100]},{"i":{"x":[0.833],"y":[0.833]},"o":{"x":[0.167],"y":[0.167]},"t":51,"s":[59]},{"i":{"x":[0.833],"y":[0.833]},"o":{"x":[0.167],"y":[0.167]},"t":52,"s":[53]},{"i":{"x":[0.833],"y":[0.833]},"o":{"x":[0.167],"y":[0.167]},"t":53,"s":[49]},{"i":{"x":[0.833],"y":[0.833]},"o":{"x":[0.167],"y":[0.167]},"t":54,"s":[51.5]},{"i":{"x":[0.833],"y":[0.833]},"o":{"x":[0.167],"y":[0.167]},"t":56,"s":[56]},{"i":{"x":[0.833],"y":[0.833]},"o":{"x":[0.167],"y":[0.167]},"t":58,"s":[59]},{"i":{"x":[0.833],"y":[0.833]},"o":{"x":[0.167],"y":[0.167]},"t":59,"s":[54]},{"i":{"x":[0.833],"y":[0.833]},"o":{"x":[0.167],"y":[0.167]},"t":60,"s":[56]},{"i":{"x":[0.833],"y":[0.833]},"o":{"x":[0.167],"y":[0.167]},"t":61,"s":[57.5]},{"i":{"x":[0.833],"y":[0.833]},"o":{"x":[0.167],"y":[0.167]},"t":62,"s":[57]},{"i":{"x":[0.833],"y":[0.833]},"o":{"x":[0.167],"y":[0.167]},"t":63,"s":[100]},{"i":{"x":[0.833],"y":[0.833]},"o":{"x":[0.167],"y":[0.167]},"t":64,"s":[100]},{"i":{"x":[0.833],"y":[0.833]},"o":{"x":[0.167],"y":[0.167]},"t":66,"s":[100]},{"i":{"x":[0.833],"y":[0.833]},"o":{"x":[0.167],"y":[0.167]},"t":67,"s":[59]},{"i":{"x":[0.833],"y":[0.833]},"o":{"x":[0.167],"y":[0.167]},"t":68,"s":[53]},{"i":{"x":[0.833],"y":[0.833]},"o":{"x":[0.167],"y":[0.167]},"t":69,"s":[49]},{"i":{"x":[0.833],"y":[0.833]},"o":{"x":[0.167],"y":[0.167]},"t":70,"s":[51.5]},{"i":{"x":[0.833],"y":[0.833]},"o":{"x":[0.167],"y":[0.167]},"t":72,"s":[56]},{"i":{"x":[0.833],"y":[0.833]},"o":{"x":[0.167],"y":[0.167]},"t":74,"s":[59]},{"i":{"x":[0.833],"y":[0.833]},"o":{"x":[0.167],"y":[0.167]},"t":75,"s":[54]},{"i":{"x":[0.833],"y":[0.833]},"o":{"x":[0.167],"y":[0.167]},"t":76,"s":[56]},{"i":{"x":[0.833],"y":[0.833]},"o":{"x":[0.167],"y":[0.167]},"t":77,"s":[57.5]},{"i":{"x":[0.833],"y":[0.833]},"o":{"x":[0.167],"y":[0.167]},"t":78,"s":[57]},{"i":{"x":[0.833],"y":[0.833]},"o":{"x":[0.167],"y":[0.167]},"t":79,"s":[100]},{"i":{"x":[0.833],"y":[0.833]},"o":{"x":[0.167],"y":[0.167]},"t":80,"s":[100]},{"i":{"x":[0.833],"y":[0.833]},"o":{"x":[0.167],"y":[0.167]},"t":82,"s":[100]},{"i":{"x":[0.833],"y":[0.833]},"o":{"x":[0.167],"y":[0.167]},"t":83,"s":[59]},{"i":{"x":[0.833],"y":[0.833]},"o":{"x":[0.167],"y":[0.167]},"t":84,"s":[53]},{"i":{"x":[0.833],"y":[0.833]},"o":{"x":[0.167],"y":[0.167]},"t":85,"s":[49]},{"i":{"x":[0.833],"y":[0.833]},"o":{"x":[0.167],"y":[0.167]},"t":86,"s":[51.5]},{"i":{"x":[0.833],"y":[0.833]},"o":{"x":[0.167],"y":[0.167]},"t":88,"s":[56]},{"i":{"x":[0.833],"y":[0.833]},"o":{"x":[0.167],"y":[0.167]},"t":90,"s":[59]},{"i":{"x":[0.833],"y":[0.833]},"o":{"x":[0.167],"y":[0.167]},"t":91,"s":[54]},{"i":{"x":[0.833],"y":[0.833]},"o":{"x":[0.167],"y":[0.167]},"t":92,"s":[56]},{"i":{"x":[0.833],"y":[0.833]},"o":{"x":[0.167],"y":[0.167]},"t":93,"s":[57.5]},{"i":{"x":[0.833],"y":[0.833]},"o":{"x":[0.167],"y":[0.167]},"t":94,"s":[57]},{"i":{"x":[0.833],"y":[0.833]},"o":{"x":[0.167],"y":[0.167]},"t":95,"s":[100]},{"i":{"x":[0.833],"y":[0.833]},"o":{"x":[0.167],"y":[0.167]},"t":96,"s":[100]},{"i":{"x":[0.833],"y":[0.833]},"o":{"x":[0.167],"y":[0.167]},"t":98,"s":[100]},{"i":{"x":[0.833],"y":[0.833]},"o":{"x":[0.167],"y":[0.167]},"t":99,"s":[59]},{"i":{"x":[0.833],"y":[0.833]},"o":{"x":[0.167],"y":[0.167]},"t":100,"s":[53]},{"i":{"x":[0.833],"y":[0.833]},"o":{"x":[0.167],"y":[0.167]},"t":101,"s":[49]},{"i":{"x":[0.833],"y":[0.833]},"o":{"x":[0.167],"y":[0.167]},"t":102,"s":[51.5]},{"i":{"x":[0.833],"y":[0.833]},"o":{"x":[0.167],"y":[0.167]},"t":104,"s":[56]},{"i":{"x":[0.833],"y":[0.833]},"o":{"x":[0.167],"y":[0.167]},"t":106,"s":[59]},{"i":{"x":[0.833],"y":[0.833]},"o":{"x":[0.167],"y":[0.167]},"t":107,"s":[54]},{"i":{"x":[0.833],"y":[0.833]},"o":{"x":[0.167],"y":[0.167]},"t":108,"s":[56]},{"i":{"x":[0.833],"y":[0.833]},"o":{"x":[0.167],"y":[0.167]},"t":109,"s":[57.5]},{"i":{"x":[0.833],"y":[0.833]},"o":{"x":[0.167],"y":[0.167]},"t":110,"s":[57]},{"i":{"x":[0.833],"y":[0.833]},"o":{"x":[0.167],"y":[0.167]},"t":111,"s":[100]},{"i":{"x":[0.833],"y":[0.833]},"o":{"x":[0.167],"y":[0.167]},"t":112,"s":[100]},{"i":{"x":[0.833],"y":[0.833]},"o":{"x":[0.167],"y":[0.167]},"t":114,"s":[100]},{"i":{"x":[0.833],"y":[0.833]},"o":{"x":[0.167],"y":[0.167]},"t":115,"s":[59]},{"i":{"x":[0.833],"y":[0.833]},"o":{"x":[0.167],"y":[0.167]},"t":116,"s":[53]},{"i":{"x":[0.833],"y":[0.833]},"o":{"x":[0.167],"y":[0.167]},"t":117,"s":[49]},{"i":{"x":[0.833],"y":[0.833]},"o":{"x":[0.167],"y":[0.167]},"t":118,"s":[51.5]},{"i":{"x":[0.833],"y":[0.833]},"o":{"x":[0.167],"y":[0.167]},"t":120,"s":[56]},{"i":{"x":[0.833],"y":[0.833]},"o":{"x":[0.167],"y":[0.167]},"t":122,"s":[59]},{"i":{"x":[0.833],"y":[0.833]},"o":{"x":[0.167],"y":[0.167]},"t":123,"s":[54]},{"i":{"x":[0.833],"y":[0.833]},"o":{"x":[0.167],"y":[0.167]},"t":124,"s":[56]},{"i":{"x":[0.833],"y":[0.833]},"o":{"x":[0.167],"y":[0.167]},"t":125,"s":[57.5]},{"i":{"x":[0.833],"y":[0.833]},"o":{"x":[0.167],"y":[0.167]},"t":126,"s":[57]},{"i":{"x":[0.833],"y":[0.833]},"o":{"x":[0.167],"y":[0.167]},"t":127,"s":[100]},{"i":{"x":[0.833],"y":[0.833]},"o":{"x":[0.167],"y":[0.167]},"t":128,"s":[100]},{"i":{"x":[0.833],"y":[0.833]},"o":{"x":[0.167],"y":[0.167]},"t":130,"s":[100]},{"i":{"x":[0.833],"y":[0.833]},"o":{"x":[0.167],"y":[0.167]},"t":131,"s":[59]},{"i":{"x":[0.833],"y":[0.833]},"o":{"x":[0.167],"y":[0.167]},"t":132,"s":[53]},{"i":{"x":[0.833],"y":[0.833]},"o":{"x":[0.167],"y":[0.167]},"t":133,"s":[49]},{"i":{"x":[0.833],"y":[0.833]},"o":{"x":[0.167],"y":[0.167]},"t":134,"s":[51.5]},{"i":{"x":[0.833],"y":[0.833]},"o":{"x":[0.167],"y":[0.167]},"t":136,"s":[56]},{"i":{"x":[0.833],"y":[0.833]},"o":{"x":[0.167],"y":[0.167]},"t":138,"s":[59]},{"i":{"x":[0.833],"y":[0.833]},"o":{"x":[0.167],"y":[0.167]},"t":139,"s":[54]},{"i":{"x":[0.833],"y":[0.833]},"o":{"x":[0.167],"y":[0.167]},"t":140,"s":[56]},{"i":{"x":[0.833],"y":[0.833]},"o":{"x":[0.167],"y":[0.167]},"t":141,"s":[57.5]},{"i":{"x":[0.833],"y":[0.833]},"o":{"x":[0.167],"y":[0.167]},"t":142,"s":[57]},{"i":{"x":[0.833],"y":[0.833]},"o":{"x":[0.167],"y":[0.167]},"t":143,"s":[100]},{"i":{"x":[0.833],"y":[0.833]},"o":{"x":[0.167],"y":[0.167]},"t":144,"s":[100]},{"i":{"x":[0.833],"y":[0.833]},"o":{"x":[0.167],"y":[0.167]},"t":146,"s":[100]},{"i":{"x":[0.833],"y":[0.833]},"o":{"x":[0.167],"y":[0.167]},"t":147,"s":[59]},{"i":{"x":[0.833],"y":[0.833]},"o":{"x":[0.167],"y":[0.167]},"t":148,"s":[53]},{"i":{"x":[0.833],"y":[0.833]},"o":{"x":[0.167],"y":[0.167]},"t":149,"s":[49]},{"i":{"x":[0.833],"y":[0.833]},"o":{"x":[0.167],"y":[0.167]},"t":150,"s":[51.5]},{"i":{"x":[0.833],"y":[0.833]},"o":{"x":[0.167],"y":[0.167]},"t":152,"s":[56]},{"i":{"x":[0.833],"y":[0.833]},"o":{"x":[0.167],"y":[0.167]},"t":154,"s":[59]},{"i":{"x":[0.833],"y":[0.833]},"o":{"x":[0.167],"y":[0.167]},"t":155,"s":[54]},{"i":{"x":[0.833],"y":[0.833]},"o":{"x":[0.167],"y":[0.167]},"t":156,"s":[56]},{"i":{"x":[0.833],"y":[0.833]},"o":{"x":[0.167],"y":[0.167]},"t":157,"s":[57.5]},{"i":{"x":[0.833],"y":[0.833]},"o":{"x":[0.167],"y":[0.167]},"t":158,"s":[57]},{"i":{"x":[0.833],"y":[0.833]},"o":{"x":[0.167],"y":[0.167]},"t":159,"s":[100]},{"i":{"x":[0.833],"y":[0.833]},"o":{"x":[0.167],"y":[0.167]},"t":160,"s":[100]},{"i":{"x":[0.833],"y":[0.833]},"o":{"x":[0.167],"y":[0.167]},"t":162,"s":[100]},{"i":{"x":[0.833],"y":[0.833]},"o":{"x":[0.167],"y":[0.167]},"t":163,"s":[59]},{"i":{"x":[0.11],"y":[1]},"o":{"x":[0.167],"y":[0.167]},"t":164,"s":[60]},{"t":165,"s":[100]}],"ix":2},"o":{"a":0,"k":0,"ix":3},"m":1,"ix":2,"nm":"Trim Paths 1","mn":"ADBE Vector Filter - Trim","hd":false},{"ty":"st","c":{"a":0,"k":[0.031372550875,0.639215707779,0.521568655968,1],"ix":3,"x":"var $bm_rt;\n$bm_rt = thisComp.layer('Color  & Stroke Change').effect('Primary')('Color');"},"o":{"a":0,"k":100,"ix":4},"w":{"a":0,"k":12,"ix":5,"x":"var $bm_rt;\n$bm_rt = $bm_mul(17.2 \/ 100, thisComp.layer('Color  & Stroke Change').effect('Stroke')('Slider'));"},"lc":2,"lj":2,"bm":0,"nm":"Stroke 1","mn":"ADBE Vector Graphic - Stroke","hd":false},{"ty":"tr","p":{"a":0,"k":[0,0],"ix":2},"a":{"a":0,"k":[0,0],"ix":1},"s":{"a":0,"k":[100,100],"ix":3},"r":{"a":0,"k":0,"ix":6},"o":{"a":0,"k":100,"ix":7},"sk":{"a":0,"k":0,"ix":4},"sa":{"a":0,"k":0,"ix":5},"nm":"Transform"}],"nm":"Group 1","np":3,"cix":2,"bm":0,"ix":1,"mn":"ADBE Vector Group","hd":false}],"ip":0,"op":844,"st":0,"bm":0},{"ddd":0,"ind":9,"ty":4,"nm":"outline","parent":5,"sr":1,"ks":{"o":{"a":0,"k":100,"ix":11},"r":{"a":0,"k":0,"ix":10},"p":{"a":0,"k":[156.356,188.286,0],"ix":2,"l":2},"a":{"a":0,"k":[0,0,0],"ix":1,"l":2},"s":{"a":0,"k":[100,100,100],"ix":6,"l":2}},"ao":0,"shapes":[{"ty":"gr","it":[{"ind":0,"ty":"sh","ix":1,"ks":{"a":1,"k":[{"i":{"x":0.667,"y":1},"o":{"x":0.333,"y":0},"t":0,"s":[{"i":[[0,0],[51.664,2.986],[0,-7.86],[-16.383,0.937],[0,0]],"o":[[0,0],[-9.583,-0.554],[0,16.64],[71.434,-4.084],[0,0]],"v":[[77.17,-13.132],[-63.52,-21.772],[-77.98,-8.172],[-48.04,21.798],[77.98,14.108]],"c":false}]},{"i":{"x":0.833,"y":0.833},"o":{"x":0.333,"y":0},"t":2,"s":[{"i":[[0,0],[50.593,10.883],[1.207,-7.767],[-16.333,-1.59],[0,0]],"o":[[0,0],[-9.385,-2.019],[-2.555,16.443],[71.214,6.933],[0,0]],"v":[[77.17,-13.132],[-59.216,-39.574],[-75.593,-28.355],[-50.61,5.856],[77.98,14.108]],"c":false}]},{"i":{"x":0.667,"y":1},"o":{"x":0.167,"y":0.167},"t":5,"s":[{"i":[[0,0],[49.301,15.906],[2.364,-9.715],[-16.2,-2.716],[0,0]],"o":[[0,0],[-9.145,-2.95],[-5.004,20.567],[70.637,11.842],[0,0]],"v":[[77.17,-13.132],[-56.133,-10.273],[-74.274,3.117],[-54.196,47.238],[77.98,14.108]],"c":false}]},{"i":{"x":0.833,"y":0.833},"o":{"x":0.333,"y":0},"t":10,"s":[{"i":[[0,0],[35.382,-37.766],[-6.036,-5.034],[-9.773,13.182],[0,0]],"o":[[0,0],[-6.563,7.005],[12.78,10.657],[42.614,-57.477],[0,0]],"v":[[77.17,-13.132],[-31.872,83.202],[-30.689,103.017],[11.504,99.218],[77.73,25.358]],"c":false}]},{"i":{"x":0.667,"y":1},"o":{"x":0.167,"y":0.167},"t":14,"s":[{"i":[[0,0],[58.934,-25.51],[-5.619,-10.781],[-17.342,10.673],[0,0]],"o":[[0,0],[-10.932,4.732],[11.897,22.824],[75.614,-46.536],[0,0]],"v":[[77.17,-13.132],[-70.555,17.203],[-76.729,44.143],[-22.387,68.094],[77.98,14.108]],"c":false}]},{"i":{"x":0.833,"y":0.833},"o":{"x":0.333,"y":0},"t":18,"s":[{"i":[[0,0],[50.593,10.883],[1.207,-7.767],[-16.333,-1.59],[0,0]],"o":[[0,0],[-9.385,-2.019],[-2.555,16.443],[71.214,6.933],[0,0]],"v":[[77.17,-13.132],[-59.216,-39.574],[-75.593,-28.355],[-50.61,5.856],[77.98,14.108]],"c":false}]},{"i":{"x":0.667,"y":1},"o":{"x":0.167,"y":0.167},"t":21,"s":[{"i":[[0,0],[49.301,15.906],[2.364,-9.715],[-16.2,-2.716],[0,0]],"o":[[0,0],[-9.145,-2.95],[-5.004,20.567],[70.637,11.842],[0,0]],"v":[[77.17,-13.132],[-56.133,-10.273],[-74.274,3.117],[-54.196,47.238],[77.98,14.108]],"c":false}]},{"i":{"x":0.833,"y":0.833},"o":{"x":0.333,"y":0},"t":26,"s":[{"i":[[0,0],[35.382,-37.766],[-6.036,-5.034],[-9.773,13.182],[0,0]],"o":[[0,0],[-6.563,7.005],[12.78,10.657],[42.614,-57.477],[0,0]],"v":[[77.17,-13.132],[-31.872,83.202],[-30.689,103.017],[11.504,99.218],[77.73,25.358]],"c":false}]},{"i":{"x":0.667,"y":1},"o":{"x":0.167,"y":0.167},"t":30,"s":[{"i":[[0,0],[58.934,-25.51],[-5.619,-10.781],[-17.342,10.673],[0,0]],"o":[[0,0],[-10.932,4.732],[11.897,22.824],[75.614,-46.536],[0,0]],"v":[[77.17,-13.132],[-70.555,17.203],[-76.729,44.143],[-22.387,68.094],[77.98,14.108]],"c":false}]},{"i":{"x":0.833,"y":0.833},"o":{"x":0.333,"y":0},"t":34,"s":[{"i":[[0,0],[50.593,10.883],[1.207,-7.767],[-16.333,-1.59],[0,0]],"o":[[0,0],[-9.385,-2.019],[-2.555,16.443],[71.214,6.933],[0,0]],"v":[[77.17,-13.132],[-59.216,-39.574],[-75.593,-28.355],[-50.61,5.856],[77.98,14.108]],"c":false}]},{"i":{"x":0.667,"y":1},"o":{"x":0.167,"y":0.167},"t":37,"s":[{"i":[[0,0],[49.301,15.906],[2.364,-9.715],[-16.2,-2.716],[0,0]],"o":[[0,0],[-9.145,-2.95],[-5.004,20.567],[70.637,11.842],[0,0]],"v":[[77.17,-13.132],[-56.133,-10.273],[-74.274,3.117],[-54.196,47.238],[77.98,14.108]],"c":false}]},{"i":{"x":0.833,"y":0.833},"o":{"x":0.333,"y":0},"t":42,"s":[{"i":[[0,0],[35.382,-37.766],[-6.036,-5.034],[-9.773,13.182],[0,0]],"o":[[0,0],[-6.563,7.005],[12.78,10.657],[42.614,-57.477],[0,0]],"v":[[77.17,-13.132],[-31.872,83.202],[-30.689,103.017],[11.504,99.218],[77.73,25.358]],"c":false}]},{"i":{"x":0.667,"y":1},"o":{"x":0.167,"y":0.167},"t":46,"s":[{"i":[[0,0],[58.934,-25.51],[-5.619,-10.781],[-17.342,10.673],[0,0]],"o":[[0,0],[-10.932,4.732],[11.897,22.824],[75.614,-46.536],[0,0]],"v":[[77.17,-13.132],[-70.555,17.203],[-76.729,44.143],[-22.387,68.094],[77.98,14.108]],"c":false}]},{"i":{"x":0.833,"y":0.833},"o":{"x":0.333,"y":0},"t":50,"s":[{"i":[[0,0],[50.593,10.883],[1.207,-7.767],[-16.333,-1.59],[0,0]],"o":[[0,0],[-9.385,-2.019],[-2.555,16.443],[71.214,6.933],[0,0]],"v":[[77.17,-13.132],[-59.216,-39.574],[-75.593,-28.355],[-50.61,5.856],[77.98,14.108]],"c":false}]},{"i":{"x":0.667,"y":1},"o":{"x":0.167,"y":0.167},"t":53,"s":[{"i":[[0,0],[49.301,15.906],[2.364,-9.715],[-16.2,-2.716],[0,0]],"o":[[0,0],[-9.145,-2.95],[-5.004,20.567],[70.637,11.842],[0,0]],"v":[[77.17,-13.132],[-56.133,-10.273],[-74.274,3.117],[-54.196,47.238],[77.98,14.108]],"c":false}]},{"i":{"x":0.833,"y":0.833},"o":{"x":0.333,"y":0},"t":58,"s":[{"i":[[0,0],[35.382,-37.766],[-6.036,-5.034],[-9.773,13.182],[0,0]],"o":[[0,0],[-6.563,7.005],[12.78,10.657],[42.614,-57.477],[0,0]],"v":[[77.17,-13.132],[-31.872,83.202],[-30.689,103.017],[11.504,99.218],[77.73,25.358]],"c":false}]},{"i":{"x":0.667,"y":1},"o":{"x":0.167,"y":0.167},"t":62,"s":[{"i":[[0,0],[58.934,-25.51],[-5.619,-10.781],[-17.342,10.673],[0,0]],"o":[[0,0],[-10.932,4.732],[11.897,22.824],[75.614,-46.536],[0,0]],"v":[[77.17,-13.132],[-70.555,17.203],[-76.729,44.143],[-22.387,68.094],[77.98,14.108]],"c":false}]},{"i":{"x":0.833,"y":0.833},"o":{"x":0.333,"y":0},"t":66,"s":[{"i":[[0,0],[50.593,10.883],[1.207,-7.767],[-16.333,-1.59],[0,0]],"o":[[0,0],[-9.385,-2.019],[-2.555,16.443],[71.214,6.933],[0,0]],"v":[[77.17,-13.132],[-59.216,-39.574],[-75.593,-28.355],[-50.61,5.856],[77.98,14.108]],"c":false}]},{"i":{"x":0.667,"y":1},"o":{"x":0.167,"y":0.167},"t":69,"s":[{"i":[[0,0],[49.301,15.906],[2.364,-9.715],[-16.2,-2.716],[0,0]],"o":[[0,0],[-9.145,-2.95],[-5.004,20.567],[70.637,11.842],[0,0]],"v":[[77.17,-13.132],[-56.133,-10.273],[-74.274,3.117],[-54.196,47.238],[77.98,14.108]],"c":false}]},{"i":{"x":0.833,"y":0.833},"o":{"x":0.333,"y":0},"t":74,"s":[{"i":[[0,0],[35.382,-37.766],[-6.036,-5.034],[-9.773,13.182],[0,0]],"o":[[0,0],[-6.563,7.005],[12.78,10.657],[42.614,-57.477],[0,0]],"v":[[77.17,-13.132],[-31.872,83.202],[-30.689,103.017],[11.504,99.218],[77.73,25.358]],"c":false}]},{"i":{"x":0.667,"y":1},"o":{"x":0.167,"y":0.167},"t":78,"s":[{"i":[[0,0],[58.934,-25.51],[-5.619,-10.781],[-17.342,10.673],[0,0]],"o":[[0,0],[-10.932,4.732],[11.897,22.824],[75.614,-46.536],[0,0]],"v":[[77.17,-13.132],[-70.555,17.203],[-76.729,44.143],[-22.387,68.094],[77.98,14.108]],"c":false}]},{"i":{"x":0.833,"y":0.833},"o":{"x":0.333,"y":0},"t":82,"s":[{"i":[[0,0],[50.593,10.883],[1.207,-7.767],[-16.333,-1.59],[0,0]],"o":[[0,0],[-9.385,-2.019],[-2.555,16.443],[71.214,6.933],[0,0]],"v":[[77.17,-13.132],[-59.216,-39.574],[-75.593,-28.355],[-50.61,5.856],[77.98,14.108]],"c":false}]},{"i":{"x":0.667,"y":1},"o":{"x":0.167,"y":0.167},"t":85,"s":[{"i":[[0,0],[49.301,15.906],[2.364,-9.715],[-16.2,-2.716],[0,0]],"o":[[0,0],[-9.145,-2.95],[-5.004,20.567],[70.637,11.842],[0,0]],"v":[[77.17,-13.132],[-56.133,-10.273],[-74.274,3.117],[-54.196,47.238],[77.98,14.108]],"c":false}]},{"i":{"x":0.833,"y":0.833},"o":{"x":0.333,"y":0},"t":90,"s":[{"i":[[0,0],[35.382,-37.766],[-6.036,-5.034],[-9.773,13.182],[0,0]],"o":[[0,0],[-6.563,7.005],[12.78,10.657],[42.614,-57.477],[0,0]],"v":[[77.17,-13.132],[-31.872,83.202],[-30.689,103.017],[11.504,99.218],[77.73,25.358]],"c":false}]},{"i":{"x":0.667,"y":1},"o":{"x":0.167,"y":0.167},"t":94,"s":[{"i":[[0,0],[58.934,-25.51],[-5.619,-10.781],[-17.342,10.673],[0,0]],"o":[[0,0],[-10.932,4.732],[11.897,22.824],[75.614,-46.536],[0,0]],"v":[[77.17,-13.132],[-70.555,17.203],[-76.729,44.143],[-22.387,68.094],[77.98,14.108]],"c":false}]},{"i":{"x":0.833,"y":0.833},"o":{"x":0.333,"y":0},"t":98,"s":[{"i":[[0,0],[50.593,10.883],[1.207,-7.767],[-16.333,-1.59],[0,0]],"o":[[0,0],[-9.385,-2.019],[-2.555,16.443],[71.214,6.933],[0,0]],"v":[[77.17,-13.132],[-59.216,-39.574],[-75.593,-28.355],[-50.61,5.856],[77.98,14.108]],"c":false}]},{"i":{"x":0.667,"y":1},"o":{"x":0.167,"y":0.167},"t":101,"s":[{"i":[[0,0],[49.301,15.906],[2.364,-9.715],[-16.2,-2.716],[0,0]],"o":[[0,0],[-9.145,-2.95],[-5.004,20.567],[70.637,11.842],[0,0]],"v":[[77.17,-13.132],[-56.133,-10.273],[-74.274,3.117],[-54.196,47.238],[77.98,14.108]],"c":false}]},{"i":{"x":0.833,"y":0.833},"o":{"x":0.333,"y":0},"t":106,"s":[{"i":[[0,0],[35.382,-37.766],[-6.036,-5.034],[-9.773,13.182],[0,0]],"o":[[0,0],[-6.563,7.005],[12.78,10.657],[42.614,-57.477],[0,0]],"v":[[77.17,-13.132],[-31.872,83.202],[-30.689,103.017],[11.504,99.218],[77.73,25.358]],"c":false}]},{"i":{"x":0.667,"y":1},"o":{"x":0.167,"y":0.167},"t":110,"s":[{"i":[[0,0],[58.934,-25.51],[-5.619,-10.781],[-17.342,10.673],[0,0]],"o":[[0,0],[-10.932,4.732],[11.897,22.824],[75.614,-46.536],[0,0]],"v":[[77.17,-13.132],[-70.555,17.203],[-76.729,44.143],[-22.387,68.094],[77.98,14.108]],"c":false}]},{"i":{"x":0.833,"y":0.833},"o":{"x":0.333,"y":0},"t":114,"s":[{"i":[[0,0],[50.593,10.883],[1.207,-7.767],[-16.333,-1.59],[0,0]],"o":[[0,0],[-9.385,-2.019],[-2.555,16.443],[71.214,6.933],[0,0]],"v":[[77.17,-13.132],[-59.216,-39.574],[-75.593,-28.355],[-50.61,5.856],[77.98,14.108]],"c":false}]},{"i":{"x":0.667,"y":1},"o":{"x":0.167,"y":0.167},"t":117,"s":[{"i":[[0,0],[49.301,15.906],[2.364,-9.715],[-16.2,-2.716],[0,0]],"o":[[0,0],[-9.145,-2.95],[-5.004,20.567],[70.637,11.842],[0,0]],"v":[[77.17,-13.132],[-56.133,-10.273],[-74.274,3.117],[-54.196,47.238],[77.98,14.108]],"c":false}]},{"i":{"x":0.833,"y":0.833},"o":{"x":0.333,"y":0},"t":122,"s":[{"i":[[0,0],[35.382,-37.766],[-6.036,-5.034],[-9.773,13.182],[0,0]],"o":[[0,0],[-6.563,7.005],[12.78,10.657],[42.614,-57.477],[0,0]],"v":[[77.17,-13.132],[-31.872,83.202],[-30.689,103.017],[11.504,99.218],[77.73,25.358]],"c":false}]},{"i":{"x":0.667,"y":1},"o":{"x":0.167,"y":0.167},"t":126,"s":[{"i":[[0,0],[58.934,-25.51],[-5.619,-10.781],[-17.342,10.673],[0,0]],"o":[[0,0],[-10.932,4.732],[11.897,22.824],[75.614,-46.536],[0,0]],"v":[[77.17,-13.132],[-70.555,17.203],[-76.729,44.143],[-22.387,68.094],[77.98,14.108]],"c":false}]},{"i":{"x":0.833,"y":0.833},"o":{"x":0.333,"y":0},"t":130,"s":[{"i":[[0,0],[50.593,10.883],[1.207,-7.767],[-16.333,-1.59],[0,0]],"o":[[0,0],[-9.385,-2.019],[-2.555,16.443],[71.214,6.933],[0,0]],"v":[[77.17,-13.132],[-59.216,-39.574],[-75.593,-28.355],[-50.61,5.856],[77.98,14.108]],"c":false}]},{"i":{"x":0.667,"y":1},"o":{"x":0.167,"y":0.167},"t":133,"s":[{"i":[[0,0],[49.301,15.906],[2.364,-9.715],[-16.2,-2.716],[0,0]],"o":[[0,0],[-9.145,-2.95],[-5.004,20.567],[70.637,11.842],[0,0]],"v":[[77.17,-13.132],[-56.133,-10.273],[-74.274,3.117],[-54.196,47.238],[77.98,14.108]],"c":false}]},{"i":{"x":0.833,"y":0.833},"o":{"x":0.333,"y":0},"t":138,"s":[{"i":[[0,0],[35.382,-37.766],[-6.036,-5.034],[-9.773,13.182],[0,0]],"o":[[0,0],[-6.563,7.005],[12.78,10.657],[42.614,-57.477],[0,0]],"v":[[77.17,-13.132],[-31.872,83.202],[-30.689,103.017],[11.504,99.218],[77.73,25.358]],"c":false}]},{"i":{"x":0.667,"y":1},"o":{"x":0.167,"y":0.167},"t":142,"s":[{"i":[[0,0],[58.934,-25.51],[-5.619,-10.781],[-17.342,10.673],[0,0]],"o":[[0,0],[-10.932,4.732],[11.897,22.824],[75.614,-46.536],[0,0]],"v":[[77.17,-13.132],[-70.555,17.203],[-76.729,44.143],[-22.387,68.094],[77.98,14.108]],"c":false}]},{"i":{"x":0.833,"y":0.833},"o":{"x":0.333,"y":0},"t":146,"s":[{"i":[[0,0],[50.593,10.883],[1.207,-7.767],[-16.333,-1.59],[0,0]],"o":[[0,0],[-9.385,-2.019],[-2.555,16.443],[71.214,6.933],[0,0]],"v":[[77.17,-13.132],[-59.216,-39.574],[-75.593,-28.355],[-50.61,5.856],[77.98,14.108]],"c":false}]},{"i":{"x":0.667,"y":1},"o":{"x":0.167,"y":0.167},"t":149,"s":[{"i":[[0,0],[49.301,15.906],[2.364,-9.715],[-16.2,-2.716],[0,0]],"o":[[0,0],[-9.145,-2.95],[-5.004,20.567],[70.637,11.842],[0,0]],"v":[[77.17,-13.132],[-56.133,-10.273],[-74.274,3.117],[-54.196,47.238],[77.98,14.108]],"c":false}]},{"i":{"x":0.833,"y":0.833},"o":{"x":0.333,"y":0},"t":154,"s":[{"i":[[0,0],[35.382,-37.766],[-6.036,-5.034],[-9.773,13.182],[0,0]],"o":[[0,0],[-6.563,7.005],[12.78,10.657],[42.614,-57.477],[0,0]],"v":[[77.17,-13.132],[-31.872,83.202],[-30.689,103.017],[11.504,99.218],[77.73,25.358]],"c":false}]},{"i":{"x":0.667,"y":1},"o":{"x":0.167,"y":0.167},"t":158,"s":[{"i":[[0,0],[58.934,-25.51],[-5.619,-10.781],[-17.342,10.673],[0,0]],"o":[[0,0],[-10.932,4.732],[11.897,22.824],[75.614,-46.536],[0,0]],"v":[[77.17,-13.132],[-70.555,17.203],[-76.729,44.143],[-22.387,68.094],[77.98,14.108]],"c":false}]},{"i":{"x":0.11,"y":1},"o":{"x":0.333,"y":0},"t":162,"s":[{"i":[[0,0],[50.593,10.883],[1.207,-7.767],[-16.333,-1.59],[0,0]],"o":[[0,0],[-9.385,-2.019],[-2.555,16.443],[71.214,6.933],[0,0]],"v":[[77.17,-13.132],[-59.216,-39.574],[-75.593,-28.355],[-50.61,5.856],[77.98,14.108]],"c":false}]},{"t":180,"s":[{"i":[[0,0],[51.664,2.986],[0,-7.86],[-16.383,0.937],[0,0]],"o":[[0,0],[-9.583,-0.554],[0,16.64],[71.434,-4.084],[0,0]],"v":[[77.17,-13.132],[-63.52,-21.772],[-77.98,-8.172],[-48.04,21.798],[77.98,14.108]],"c":false}]}],"ix":2},"nm":"Path 1","mn":"ADBE Vector Shape - Group","hd":false},{"ty":"st","c":{"a":0,"k":[0.031372550875,0.639215707779,0.521568655968,1],"ix":3,"x":"var $bm_rt;\n$bm_rt = thisComp.layer('Color  & Stroke Change').effect('Primary')('Color');"},"o":{"a":0,"k":100,"ix":4},"w":{"a":0,"k":12,"ix":5,"x":"var $bm_rt;\n$bm_rt = $bm_mul(17.2 \/ 100, thisComp.layer('Color  & Stroke Change').effect('Stroke')('Slider'));"},"lc":2,"lj":2,"bm":0,"nm":"Stroke 1","mn":"ADBE Vector Graphic - Stroke","hd":false},{"ty":"tr","p":{"a":0,"k":[0,0],"ix":2},"a":{"a":0,"k":[0,0],"ix":1},"s":{"a":0,"k":[100,100],"ix":3},"r":{"a":0,"k":0,"ix":6},"o":{"a":0,"k":100,"ix":7},"sk":{"a":0,"k":0,"ix":4},"sa":{"a":0,"k":0,"ix":5},"nm":"Transform"}],"nm":"Group 1","np":2,"cix":2,"bm":0,"ix":1,"mn":"ADBE Vector Group","hd":false}],"ip":0,"op":844,"st":0,"bm":0}],"markers":[]}