{"v":"5.7.6","fr":60,"ip":0,"op":174,"w":500,"h":500,"nm":"1564-hair-washing-sink-outline","ddd":0,"assets":[],"layers":[{"ddd":0,"ind":1,"ty":3,"nm":"02092020","sr":1,"ks":{"o":{"a":0,"k":0,"ix":11},"r":{"a":0,"k":0,"ix":10},"p":{"a":0,"k":[-105,15,0],"ix":2,"l":2},"a":{"a":0,"k":[60,60,0],"ix":1,"l":2},"s":{"a":0,"k":[100,100,100],"ix":6,"l":2}},"ao":0,"ef":[{"ty":5,"nm":"02092020002","np":3,"mn":"ADBE Checkbox Control","ix":1,"en":1,"ef":[{"ty":7,"nm":"Checkbox","mn":"ADBE Checkbox Control-0001","ix":1,"v":{"a":0,"k":1,"ix":1}}]}],"ip":0,"op":300,"st":0,"bm":0},{"ddd":0,"ind":3,"ty":3,"nm":"Color  & Stroke Change","sr":1,"ks":{"o":{"a":0,"k":0,"ix":11},"r":{"a":0,"k":0,"ix":10},"p":{"a":0,"k":[0,0],"ix":2,"l":2},"a":{"a":0,"k":[0,0,0],"ix":1,"l":2},"s":{"a":0,"k":[100,100,100],"ix":6,"l":2}},"ao":0,"ef":[{"ty":5,"nm":"Primary","np":3,"mn":"ADBE Color Control","ix":1,"en":1,"ef":[{"ty":2,"nm":"Color","mn":"ADBE Color Control-0001","ix":1,"v":{"a":0,"k":[0.070588238537,0.074509806931,0.192156866193,1],"ix":1}}]},{"ty":5,"nm":"Secondary","np":3,"mn":"ADBE Color Control","ix":2,"en":1,"ef":[{"ty":2,"nm":"Color","mn":"ADBE Color Control-0001","ix":1,"v":{"a":0,"k":[0.031372550875,0.658823549747,0.541176497936,1],"ix":1}}]},{"ty":5,"nm":"Stroke","np":3,"mn":"ADBE Slider Control","ix":3,"en":1,"ef":[{"ty":0,"nm":"Slider","mn":"ADBE Slider Control-0001","ix":1,"v":{"a":0,"k":70,"ix":1}}]},{"ty":5,"nm":"Axis","np":3,"mn":"ADBE Point Control","ix":4,"en":1,"ef":[{"ty":3,"nm":"Point","mn":"ADBE Point Control-0001","ix":1,"v":{"a":0,"k":[250,250],"ix":1}}]},{"ty":5,"nm":"Scale","np":3,"mn":"ADBE Slider Control","ix":5,"en":1,"ef":[{"ty":0,"nm":"Slider","mn":"ADBE Slider Control-0001","ix":1,"v":{"a":0,"k":100,"ix":1}}]}],"ip":0,"op":300,"st":0,"bm":0},{"ddd":0,"ind":4,"ty":3,"nm":"NULL","sr":1,"ks":{"o":{"a":0,"k":0,"ix":11},"r":{"a":0,"k":0,"ix":10},"p":{"a":0,"k":[250,250,0],"ix":2,"l":2,"x":"var $bm_rt;\n$bm_rt = thisComp.layer('Color  & Stroke Change').effect('Axis')('Point');"},"a":{"a":0,"k":[60,60,0],"ix":1,"l":2},"s":{"a":0,"k":[100,100,100],"ix":6,"l":2,"x":"var $bm_rt;\nvar temp;\ntemp = thisComp.layer('Color  & Stroke Change').effect('Scale')('Slider');\n$bm_rt = [\n    temp,\n    temp\n];"}},"ao":0,"ip":0,"op":300,"st":0,"bm":0},{"ddd":0,"ind":5,"ty":4,"nm":"Shower Battery","parent":4,"sr":1,"ks":{"o":{"a":0,"k":100,"ix":11},"r":{"a":1,"k":[{"i":{"x":[0.4],"y":[1]},"o":{"x":[0.333],"y":[0]},"t":0,"s":[0]},{"i":{"x":[0.667],"y":[1]},"o":{"x":[0.6],"y":[0]},"t":60,"s":[-16]},{"i":{"x":[0.667],"y":[1]},"o":{"x":[0.333],"y":[0]},"t":117,"s":[7]},{"t":150,"s":[0]}],"ix":10},"p":{"a":1,"k":[{"i":{"x":0.4,"y":1},"o":{"x":0.333,"y":0},"t":0,"s":[-93.045,-66.716,0],"to":[-4.167,0,0],"ti":[6.542,0.25,0]},{"i":{"x":0.667,"y":1},"o":{"x":0.6,"y":0},"t":60,"s":[-118.045,-66.716,0],"to":[0.833,1.5,0],"ti":[-4.167,0,0]},{"i":{"x":0.667,"y":1},"o":{"x":0.333,"y":0},"t":117,"s":[-88.045,-57.716,0],"to":[-3.333,-2.313,0],"ti":[0.833,1.5,0]},{"t":150,"s":[-93.045,-66.716,0]}],"ix":2,"l":2},"a":{"a":0,"k":[96.956,123.284,0],"ix":1,"l":2},"s":{"a":0,"k":[100,100,100],"ix":6,"l":2}},"ao":0,"shapes":[{"ty":"gr","it":[{"ind":0,"ty":"sh","ix":1,"ks":{"a":0,"k":{"i":[[0,0],[0,0]],"o":[[0,0],[0,0]],"v":[[0,5.333],[0,-5.333]],"c":false},"ix":2},"nm":"Path 1","mn":"ADBE Vector Shape - Group","hd":false},{"ind":1,"ty":"sh","ix":2,"ks":{"a":0,"k":{"i":[[0,0],[0,0]],"o":[[0,0],[0,0]],"v":[[-31.01,5.333],[-31.01,-5.333]],"c":false},"ix":2},"nm":"Path 2","mn":"ADBE Vector Shape - Group","hd":false},{"ind":2,"ty":"sh","ix":3,"ks":{"a":0,"k":{"i":[[0,0],[0,0],[13.332,0],[0,0],[0,13.332],[0,0]],"o":[[0,0],[0,13.332],[0,0],[-13.332,0],[0,0],[0,0]],"v":[[28.677,-29.413],[28.677,-18.807],[4.537,5.333],[-35.547,5.333],[-59.687,-18.807],[-59.687,-29.413]],"c":false},"ix":2},"nm":"Path 3","mn":"ADBE Vector Shape - Group","hd":false},{"ind":3,"ty":"sh","ix":4,"ks":{"a":0,"k":{"i":[[0,0],[0,0],[0,0],[0,0],[0,-6.203]],"o":[[0,0],[0,0],[0,0],[6.203,0],[0,0]],"v":[[28.677,-29.413],[-175.473,-29.413],[-175.473,-56.1],[17.445,-56.1],[28.677,-44.868]],"c":true},"ix":2},"nm":"Path 4","mn":"ADBE Vector Shape - Group","hd":false},{"ty":"st","c":{"a":0,"k":[0.031372550875,0.658823549747,0.541176497936,1],"ix":3,"x":"var $bm_rt;\n$bm_rt = thisComp.layer('Color  & Stroke Change').effect('Primary')('Color');"},"o":{"a":0,"k":100,"ix":4},"w":{"a":0,"k":12,"ix":5,"x":"var $bm_rt;\n$bm_rt = $bm_mul(17.1 \/ 100, thisComp.layer('Color  & Stroke Change').effect('Stroke')('Slider'));"},"lc":2,"lj":2,"bm":0,"nm":"Stroke 1","mn":"ADBE Vector Graphic - Stroke","hd":false},{"ty":"tr","p":{"a":0,"k":[265.354,167.667],"ix":2},"a":{"a":0,"k":[0,0],"ix":1},"s":{"a":0,"k":[100,100],"ix":3},"r":{"a":0,"k":0,"ix":6},"o":{"a":0,"k":100,"ix":7},"sk":{"a":0,"k":0,"ix":4},"sa":{"a":0,"k":0,"ix":5},"nm":"Transform"}],"nm":"Group 1","np":5,"cix":2,"bm":0,"ix":1,"mn":"ADBE Vector Group","hd":false}],"ip":0,"op":844,"st":0,"bm":0},{"ddd":0,"ind":6,"ty":4,"nm":"Sink","parent":4,"sr":1,"ks":{"o":{"a":0,"k":100,"ix":11},"r":{"a":0,"k":0,"ix":10},"p":{"a":0,"k":[60,146.092,0],"ix":2,"l":2},"a":{"a":0,"k":[250,336.092,0],"ix":1,"l":2},"s":{"a":0,"k":[100,100,100],"ix":6,"l":2}},"ao":0,"shapes":[{"ty":"gr","it":[{"ind":0,"ty":"sh","ix":1,"ks":{"a":0,"k":{"i":[[0,0],[0,0],[0,0],[0,0]],"o":[[0,0],[0,0],[0,0],[0,0]],"v":[[53.373,-18.158],[53.373,18.158],[-53.373,18.158],[-53.373,-18.158]],"c":false},"ix":2},"nm":"Path 1","mn":"ADBE Vector Shape - Group","hd":false},{"ind":1,"ty":"sh","ix":2,"ks":{"a":0,"k":{"i":[[0,0],[0,0],[27.802,0],[0,0],[11.156,25.466],[0,0],[0,0],[-3.772,-12.437],[0,0],[-15.157,0],[0,0],[-4.392,14.506],[0,0],[-12.996,0]],"o":[[0,0],[-11.156,25.466],[0,0],[-27.802,0],[0,0],[0,0],[12.996,0],[0,0],[4.392,14.506],[0,0],[15.157,0],[0,0],[3.772,-12.437],[0,0]],"v":[[148.982,-129.895],[118.399,-60.075],[54.273,-18.158],[-54.273,-18.158],[-118.399,-60.075],[-148.982,-129.895],[-78.602,-129.895],[-50.369,-108.955],[-45.489,-92.864],[-12.57,-68.449],[12.57,-68.449],[45.489,-92.864],[50.369,-108.955],[78.602,-129.895]],"c":true},"ix":2},"nm":"Path 2","mn":"ADBE Vector Shape - Group","hd":false},{"ty":"st","c":{"a":0,"k":[0.031372550875,0.658823549747,0.541176497936,1],"ix":3,"x":"var $bm_rt;\n$bm_rt = thisComp.layer('Color  & Stroke Change').effect('Primary')('Color');"},"o":{"a":0,"k":100,"ix":4},"w":{"a":0,"k":12,"ix":5,"x":"var $bm_rt;\n$bm_rt = $bm_mul(17.1 \/ 100, thisComp.layer('Color  & Stroke Change').effect('Stroke')('Slider'));"},"lc":2,"lj":2,"bm":0,"nm":"Stroke 1","mn":"ADBE Vector Graphic - Stroke","hd":false},{"ty":"tr","p":{"a":0,"k":[250,391.961],"ix":2},"a":{"a":0,"k":[0,0],"ix":1},"s":{"a":0,"k":[100,100],"ix":3},"r":{"a":0,"k":0,"ix":6},"o":{"a":0,"k":100,"ix":7},"sk":{"a":0,"k":0,"ix":4},"sa":{"a":0,"k":0,"ix":5},"nm":"Transform"}],"nm":"Group 1","np":3,"cix":2,"bm":0,"ix":1,"mn":"ADBE Vector Group","hd":false}],"ip":0,"op":844,"st":0,"bm":0},{"ddd":0,"ind":7,"ty":4,"nm":"Water-2","parent":5,"sr":1,"ks":{"o":{"a":0,"k":100,"ix":11},"r":{"a":0,"k":0,"ix":10,"x":"var $bm_rt;\n$bm_rt = $bm_neg(thisComp.layer('Shower Battery').transform.rotation.valueAtTime($bm_sub(time, 0.1)));"},"p":{"a":0,"k":[250,176.5,0],"ix":2,"l":2},"a":{"a":0,"k":[0,-73.5,0],"ix":1,"l":2},"s":{"a":0,"k":[100,100,100],"ix":6,"l":2}},"ao":0,"shapes":[{"ty":"gr","it":[{"ind":0,"ty":"sh","ix":1,"ks":{"a":1,"k":[{"i":{"x":0.833,"y":0.833},"o":{"x":0.333,"y":0},"t":0,"s":[{"i":[[0,0],[0,-35.778]],"o":[[0,53.667],[0,0]],"v":[[-15.5,-55.5],[-15.5,50]],"c":false}]},{"i":{"x":0.4,"y":1},"o":{"x":0.167,"y":0.167},"t":34,"s":[{"i":[[0,0],[6.538,-48.131]],"o":[[5.943,55.098],[0,0]],"v":[[-15.5,-55.5],[-12.629,105.104]],"c":false}]},{"i":{"x":0.833,"y":0.833},"o":{"x":0.6,"y":0},"t":66,"s":[{"i":[[0,0],[9.415,-53.566]],"o":[[8.557,55.727],[0,0]],"v":[[-15.5,-55.5],[-9.97,112.829]],"c":false}]},{"i":{"x":0.833,"y":0.833},"o":{"x":0.167,"y":0.167},"t":82,"s":[{"i":[[0,0],[8.231,-52.381]],"o":[[7.226,53.973],[0,0]],"v":[[-15.538,-55.467],[-9.782,99.594]],"c":false}]},{"i":{"x":0.833,"y":0.833},"o":{"x":0.167,"y":0.167},"t":100,"s":[{"i":[[0,0],[3.622,-47.766]],"o":[[2.042,47.141],[0,0]],"v":[[-15.684,-55.34],[-13.397,62.92]],"c":false}]},{"i":{"x":0.667,"y":1},"o":{"x":0.167,"y":0.167},"t":112,"s":[{"i":[[0,0],[-0.316,-43.824]],"o":[[-2.386,41.305],[0,0]],"v":[[-15.809,-55.231],[-18.406,44.711]],"c":false}]},{"i":{"x":0.667,"y":1},"o":{"x":0.333,"y":0},"t":123,"s":[{"i":[[0,0],[-2.326,-41.812]],"o":[[-4.647,38.327],[0,0]],"v":[[-15.873,-55.176],[-20.837,38.435]],"c":false}]},{"i":{"x":0.667,"y":1},"o":{"x":0.333,"y":0},"t":150,"s":[{"i":[[0,0],[-1.967,-41.333]],"o":[[0,53.667],[0,0]],"v":[[-15.5,-55.5],[-16.852,44.637]],"c":false}]},{"t":173,"s":[{"i":[[0,0],[0,-35.778]],"o":[[0,53.667],[0,0]],"v":[[-15.5,-55.5],[-15.5,50]],"c":false}]}],"ix":2},"nm":"Path 1","mn":"ADBE Vector Shape - Group","hd":false},{"ty":"st","c":{"a":0,"k":[0.031372550875,0.658823549747,0.541176497936,1],"ix":3,"x":"var $bm_rt;\n$bm_rt = thisComp.layer('Color  & Stroke Change').effect('Secondary')('Color');"},"o":{"a":0,"k":100,"ix":4},"w":{"a":0,"k":12,"ix":5,"x":"var $bm_rt;\n$bm_rt = $bm_mul(17.1 \/ 100, thisComp.layer('Color  & Stroke Change').effect('Stroke')('Slider'));"},"lc":2,"lj":2,"bm":0,"nm":"Stroke 1","mn":"ADBE Vector Graphic - Stroke","hd":false},{"ty":"tr","p":{"a":0,"k":[30.5,0],"ix":2},"a":{"a":0,"k":[0,0],"ix":1},"s":{"a":0,"k":[100,100],"ix":3},"r":{"a":0,"k":0,"ix":6},"o":{"a":0,"k":100,"ix":7},"sk":{"a":0,"k":0,"ix":4},"sa":{"a":0,"k":0,"ix":5},"nm":"Transform"}],"nm":"Shape 2","np":2,"cix":2,"bm":0,"ix":1,"mn":"ADBE Vector Group","hd":false},{"ty":"gr","it":[{"ind":0,"ty":"sh","ix":1,"ks":{"a":1,"k":[{"i":{"x":0.833,"y":0.833},"o":{"x":0.333,"y":0},"t":0,"s":[{"i":[[0,0],[0,-35.778]],"o":[[0,53.667],[0,0]],"v":[[-15.5,-55.5],[-15.5,50]],"c":false}]},{"i":{"x":0.4,"y":1},"o":{"x":0.167,"y":0.167},"t":34,"s":[{"i":[[0,0],[6.538,-48.131]],"o":[[5.943,55.098],[0,0]],"v":[[-15.5,-55.5],[-12.629,105.104]],"c":false}]},{"i":{"x":0.833,"y":0.833},"o":{"x":0.6,"y":0},"t":66,"s":[{"i":[[0,0],[9.415,-53.566]],"o":[[8.557,55.727],[0,0]],"v":[[-15.5,-55.5],[-9.97,112.829]],"c":false}]},{"i":{"x":0.833,"y":0.833},"o":{"x":0.167,"y":0.167},"t":82,"s":[{"i":[[0,0],[8.231,-52.381]],"o":[[7.226,53.973],[0,0]],"v":[[-15.538,-55.467],[-9.782,99.594]],"c":false}]},{"i":{"x":0.833,"y":0.833},"o":{"x":0.167,"y":0.167},"t":100,"s":[{"i":[[0,0],[3.622,-47.766]],"o":[[2.042,47.141],[0,0]],"v":[[-15.684,-55.34],[-13.397,62.92]],"c":false}]},{"i":{"x":0.833,"y":0.833},"o":{"x":0.167,"y":0.167},"t":104,"s":[{"i":[[0,0],[2.309,-46.452]],"o":[[0.566,45.196],[0,0]],"v":[[-15.726,-55.304],[-14.012,54.262]],"c":false}]},{"i":{"x":0.667,"y":1},"o":{"x":0.167,"y":0.167},"t":112,"s":[{"i":[[0,0],[-0.316,-43.824]],"o":[[-2.386,41.305],[0,0]],"v":[[-15.809,-55.231],[-18.406,44.711]],"c":false}]},{"i":{"x":0.667,"y":1},"o":{"x":0.333,"y":0},"t":123,"s":[{"i":[[0,0],[-2.326,-41.812]],"o":[[-4.647,38.327],[0,0]],"v":[[-15.873,-55.176],[-20.837,38.435]],"c":false}]},{"i":{"x":0.667,"y":1},"o":{"x":0.333,"y":0},"t":150,"s":[{"i":[[0,0],[-1.967,-41.333]],"o":[[0,53.667],[0,0]],"v":[[-15.5,-55.5],[-16.852,44.637]],"c":false}]},{"t":173,"s":[{"i":[[0,0],[0,-35.778]],"o":[[0,53.667],[0,0]],"v":[[-15.5,-55.5],[-15.5,50]],"c":false}]}],"ix":2},"nm":"Path 1","mn":"ADBE Vector Shape - Group","hd":false},{"ty":"st","c":{"a":0,"k":[0.031372550875,0.658823549747,0.541176497936,1],"ix":3,"x":"var $bm_rt;\n$bm_rt = thisComp.layer('Color  & Stroke Change').effect('Secondary')('Color');"},"o":{"a":0,"k":100,"ix":4},"w":{"a":0,"k":12,"ix":5,"x":"var $bm_rt;\n$bm_rt = $bm_mul(17.1 \/ 100, thisComp.layer('Color  & Stroke Change').effect('Stroke')('Slider'));"},"lc":2,"lj":2,"bm":0,"nm":"Stroke 1","mn":"ADBE Vector Graphic - Stroke","hd":false},{"ty":"tr","p":{"a":0,"k":[0,0],"ix":2},"a":{"a":0,"k":[0,0],"ix":1},"s":{"a":0,"k":[100,100],"ix":3},"r":{"a":0,"k":0,"ix":6},"o":{"a":0,"k":100,"ix":7},"sk":{"a":0,"k":0,"ix":4},"sa":{"a":0,"k":0,"ix":5},"nm":"Transform"}],"nm":"Shape 1","np":2,"cix":2,"bm":0,"ix":2,"mn":"ADBE Vector Group","hd":false}],"ip":0,"op":844,"st":0,"bm":0}],"markers":[]}